Workbook

Sheet Read me
A1: Valuation date | B1: 18 September 2026; USD millions except per-share data and explicit percentages.
A2: Inputs | B2: Blue cells are analyst assumptions. Financial facts are linked by accession and tag in Financial audit.
A3: Historical TTM | B3: FY2025 + H1 2026 - H1 2025. Reported cutoffs create a 371-day trailing period. Interim shares weighted by day count.
A4: Value-added sales | B4: 2021 and 2022 use the comparable recast figures disclosed in the FY2023 10-K. These differ from originally published VA sales.
A5: FCF | B5: Operating cash flow less PPE spending AND separately reported mine-development spending. Excludes acquisitions. Annual mining outflows: zero separately reported in 2021-22, $9.326m in 2023, $12.159m in 2024, $26.288m in 2025.
A6: Adjusted EBITDA | B6: Company-reported non-GAAP metric; 2021-22 from 2023 investor deck; 2023 from Q4 deck; 2024-25 from FY2025 release; TTM 237.2 from Q2 2026 slide 16.
A7: DCF periods | B7: Five prospective 12-month years ending September 18, 2027-2031; year-end discounting; terminal reinvestment reset to terminal growth.
A8: Balance-sheet bridge | B8: Debt principal + estimated finance leases + retirement liability - cash. Operating lease expense remains in operating forecasts.
A9: Share count | B9: 20.834m latest balance-sheet common shares for market cap; 21.15m prospective diluted shares for DCF and earnings scenarios.
A10: Capital spending | B10: Q2 deck: $75m PPE plus $25m mine development. Q2 10-Q prose says $100m PPE. Disclosure discrepancy retained in report; $100m total base anchor and $125m downside cash sensitivity.
A11: Model status | B11: Formulas include cached numerical values verified against Python; formulas recalculate when changed in Excel. Scenario and DCF assumptions are analyst estimates.
A12: Options | B12: Saved real Cboe quotes; no strategies or calculated Greeks because liquidity screen failed. Vendor Greeks remain identified as vendor values.
... A14: Rebuild | B14: Run python MTRN/code/run_analysis.py from repository root after installing MTRN/code/requirements.txt.

Sheet Historical
A1: period | B1: start | C1: end | D1: revenue | E1: gross_profit | F1: operating_income | G1: net_income | H1: tax | I1: interest | J1: cfo | K1: ppe_capex | L1: mine_capex | M1: da | N1: amortization | O1: sbc | P1: rnd | Q1: dividends | R1: repurchases | S1: diluted_shares | T1: basic_shares | U1: eps | V1: cash | W1: assets | X1: current_assets | Y1: liabilities | Z1: current_liabilities | AA1: equity | AB1: debt_current | AC1: debt_noncurrent | AD1: debt_face | AE1: goodwill | AF1: intangibles | AG1: receivables | AH1: inventory | AI1: payables | AJ1: shares_issued | AK1: treasury_shares | AL1: finance_lease_current | AM1: finance_lease_noncurrent | AN1: va_sales | AO1: adjusted_ebitda | AP1: capex | AQ1: fcf | AR1: debt | AS1: net_debt | AT1: ebitda | AU1: operating_ebitda | AV1: gross_margin | AW1: gross_margin_va | AX1: operating_margin | AY1: net_margin | AZ1: fcf_margin | BA1: sbc_revenue | BB1: current_ratio | BC1: debt_equity | BD1: actual_shares | BE1: interest_cover | BF1: fcf_per_share | BG1: fcf_conversion | BH1: adjusted_ebitda_margin_va
A2: 2021 | B2: 2021-01-01 | C2: 2021-12-31 | D2: 1510.644 | E2: 283.762 | F2: 77.111 | G2: 72.474 | H2: 4.851 | I2: 4.901 | J2: 90.241 | K2: 102.91 | L2: 0 | M2: 44.137 | N2: 5.973 | O2: 6.517 | P2: 26.575 | Q2: 9.697 | R2: 0 | S2: 20.689 | T2: 20.422 | U2: 3.5 | V2: 14.462 | W2: 1607.479 | X2: 627.252 | Y2: 887.039 | Z2: 204.509 | AA2: 720.44 | AB2: 15.359 | AC2: 434.388 | AD2: 454.548 | AE2: 318.62 | AF2: 156.736 | AG2: 213.819 | AH2: 361.115 | AI2: 86.243 | AJ2: 27.148 | AK2: 6.7 | AL2: 2.8 | AM2: 16.327 | AN2: 829.572 | AO2: 143.6 | AP2: =K2+L2 -> 102.91 | AQ2: =J2-AP2 -> -12.669 | AR2: =AB2+AC2 -> 449.747 | AS2: =AR2-V2 -> 435.285 | AT2: =G2+H2+I2+M2 -> 126.363 | AU2: =F2+M2 -> 121.248 | AV2: =E2/D2 -> 0.18784174 | AW2: =E2/AN2 -> 0.34205831 | AX2: =F2/D2 -> 0.051045117 | AY2: =G2/D2 -> 0.047975565 | AZ2: =AQ2/D2 -> -0.0083864895 | BA2: =O2/D2 -> 0.0043140541 | BB2: =X2/Z2 -> 3.067112 | BC2: =AR2/AA2 -> 0.62426711 | BD2: =AJ2-AK2 -> 20.448 | BE2: =F2/I2 -> 15.733728 | BF2: =AQ2/S2 -> -0.61235439 | BG2: =AQ2/G2 -> -0.17480752 | BH2: =AO2/AN2 -> 0.17310131
A3: 2022 | B3: 2022-01-01 | C3: 2022-12-31 | D3: 1757.109 | E3: 343.88 | F3: 119.755 | G3: 85.99 | H3: 17.11 | I3: 21.905 | J3: 115.958 | K3: 77.608 | L3: 0 | M3: 53.436 | N3: 12.4 | O3: 8.813 | P3: 28.977 | Q3: 10.16 | R3: 0 | S3: 20.76 | T3: 20.511 | U3: 4.14 | V3: 13.101 | W3: 1691.979 | X3: 690.448 | Y3: 891.989 | Z3: 238.964 | AA3: 799.99 | AB3: 21.105 | AC3: 410.876 | AD3: 435.791 | AE3: 319.498 | AF3: 139.601 | AG3: 215.211 | AH3: 423.08 | AI3: 107.899 | AJ3: 27.148 | AK3: 6.605 | AL3: 1.485 | AM3: 13.876 | AN3: 1114.411 | AO3: 196 | AP3: =K3+L3 -> 77.608 | AQ3: =J3-AP3 -> 38.35 | AR3: =AB3+AC3 -> 431.981 | AS3: =AR3-V3 -> 418.88 | AT3: =G3+H3+I3+M3 -> 178.441 | AU3: =F3+M3 -> 173.191 | AV3: =E3/D3 -> 0.19570784 | AW3: =E3/AN3 -> 0.30857556 | AX3: =F3/D3 -> 0.068154565 | AY3: =G3/D3 -> 0.048938341 | AZ3: =AQ3/D3 -> 0.021825624 | BA3: =O3/D3 -> 0.0050156251 | BB3: =X3/Z3 -> 2.889339 | BC3: =AR3/AA3 -> 0.539983 | BD3: =AJ3-AK3 -> 20.543 | BE3: =F3/I3 -> 5.4670167 | BF3: =AQ3/S3 -> 1.8473025 | BG3: =AQ3/G3 -> 0.44598209 | BH3: =AO3/AN3 -> 0.17587766
A4: 2023 | B4: 2023-01-01 | C4: 2023-12-31 | D4: 1665.187 | E4: 349.042 | F4: 136.444 | G4: 95.702 | H4: 12.129 | I4: 31.323 | J4: 144.414 | K4: 110.55 | L4: 9.326 | M4: 61.644 | N4: 12.876 | O4: 10.092 | P4: 27.54 | Q4: 10.621 | R4: 0 | S4: 20.911 | T4: 20.619 | U4: 4.58 | V4: 13.294 | W4: 1762.726 | X4: 709.382 | Y4: 877.673 | Z4: 254.995 | AA4: 885.053 | AB4: 38.597 | AC4: 387.576 | AD4: 428.993 | AE4: 320.873 | AF4: 133.571 | AG4: 192.747 | AH4: 441.597 | AI4: 125.663 | AJ4: 27.148 | AK4: 6.502 | AL4: 0.626 | AM4: 13.744 | AN4: 1127.071 | AO4: 217.7 | AP4: =K4+L4 -> 119.876 | AQ4: =J4-AP4 -> 24.538 | AR4: =AB4+AC4 -> 426.173 | AS4: =AR4-V4 -> 412.879 | AT4: =G4+H4+I4+M4 -> 200.798 | AU4: =F4+M4 -> 198.088 | AV4: =E4/D4 -> 0.20961129 | AW4: =E4/AN4 -> 0.30968945 | AX4: =F4/D4 -> 0.081939146 | AY4: =G4/D4 -> 0.057472224 | AZ4: =AQ4/D4 -> 0.014735883 | BA4: =O4/D4 -> 0.0060605806 | BB4: =X4/Z4 -> 2.7819447 | BC4: =AR4/AA4 -> 0.48152258 | BD4: =AJ4-AK4 -> 20.646 | BE4: =F4/I4 -> 4.3560323 | BF4: =AQ4/S4 -> 1.1734494 | BG4: =AQ4/G4 -> 0.25640008 | BH4: =AO4/AN4 -> 0.19315553
A5: 2024 | B5: 2024-01-01 | C5: 2024-12-31 | D5: 1684.739 | E5: 325.985 | F5: 47.223 | G5: 5.888 | H5: 9.014 | I5: 34.764 | J5: 87.817 | K5: 68.649 | L5: 12.159 | M5: 68.676 | N5: 12.134 | O5: 10.56 | P5: 29.028 | Q5: 11.087 | R5: 0 | S5: 20.928 | T5: 20.732 | U5: 0.28 | V5: 16.713 | W5: 1697.632 | X5: 724.224 | Y5: 828.751 | Z5: 226.734 | AA5: 868.881 | AB5: 34.274 | AC5: 407.734 | AD5: 443.899 | AE5: 263.738 | AF5: 109.312 | AG5: 193.793 | AH5: 441.299 | AI5: 105.901 | AJ5: 27.148 | AK5: 6.384 | AL5: 0.552 | AM5: 12.404 | AN5: 1097.577 | AO5: 221.2 | AP5: =K5+L5 -> 80.808 | AQ5: =J5-AP5 -> 7.009 | AR5: =AB5+AC5 -> 442.008 | AS5: =AR5-V5 -> 425.295 | AT5: =G5+H5+I5+M5 -> 118.342 | AU5: =F5+M5 -> 115.899 | AV5: =E5/D5 -> 0.19349288 | AW5: =E5/AN5 -> 0.29700422 | AX5: =F5/D5 -> 0.028029861 | AY5: =G5/D5 -> 0.0034949034 | AZ5: =AQ5/D5 -> 0.0041602883 | BA5: =O5/D5 -> 0.0062680332 | BB5: =X5/Z5 -> 3.194157 | BC5: =AR5/AA5 -> 0.50870948 | BD5: =AJ5-AK5 -> 20.764 | BE5: =F5/I5 -> 1.358388 | BF5: =AQ5/S5 -> 0.33491017 | BG5: =AQ5/G5 -> 1.1903872 | BH5: =AO5/AN5 -> 0.20153484
A6: 2025 | B6: 2025-01-01 | C6: 2025-12-31 | D6: 1786.55 | E6: 308.626 | F6: 109.796 | G6: 74.823 | H6: 6.718 | I6: 30.692 | J6: 103.243 | K6: 53.279 | L6: 26.288 | M6: 69.074 | N6: 11.013 | O6: 10.925 | P6: 25.941 | Q6: 11.51 | R6: 7.843 | S6: 20.912 | T6: 20.755 | U6: 3.58 | V6: 13.681 | W6: 1802.801 | X6: 789.52 | Y6: 859.524 | Z6: 253.583 | AA6: 943.277 | AB6: 22.445 | AC6: 436.348 | AD6: 460.642 | AE6: 280.657 | AF6: 105.874 | AG6: 222.916 | AH6: 461.231 | AI6: 148.642 | AJ6: 27.148 | AK6: 6.413 | AL6: 0.622 | AM6: 13.384 | AN6: 1046.194 | AO6: 217 | AP6: =K6+L6 -> 79.567 | AQ6: =J6-AP6 -> 23.676 | AR6: =AB6+AC6 -> 458.793 | AS6: =AR6-V6 -> 445.112 | AT6: =G6+H6+I6+M6 -> 181.307 | AU6: =F6+M6 -> 178.87 | AV6: =E6/D6 -> 0.17274971 | AW6: =E6/AN6 -> 0.29499882 | AX6: =F6/D6 -> 0.061456998 | AY6: =G6/D6 -> 0.04188128 | AZ6: =AQ6/D6 -> 0.013252358 | BA6: =O6/D6 -> 0.0061151381 | BB6: =X6/Z6 -> 3.1134579 | BC6: =AR6/AA6 -> 0.48638205 | BD6: =AJ6-AK6 -> 20.735 | BE6: =F6/I6 -> 3.5773491 | BF6: =AQ6/S6 -> 1.1321729 | BG6: =AQ6/G6 -> 0.31642677 | BH6: =AO6/AN6 -> 0.20741851
A7: H1 2025 | B7: 2025-01-01 | C7: 2025-06-27 | D7: 851.988 | E7: 158.837 | F7: 64.014 | G7: 42.838 | H7: 7.262 | I7: 15.147 | J7: 65.442 | K7: 25.003 | L7: 10.175 | M7: 34.047 | N7: 5.695 | O7: 5.437 | P7: 12.918 | Q7: 5.705 | R7: 7.843 | S7: 20.874 | T7: 20.779 | U7: 2.05 | V7: 12.591 | W7: 1741.207 | X7: 735.113 | Y7: 830.562 | Z7: 231.901 | AA7: 910.645 | AB7: 19.88 | AC7: 405.697 | AD7: 427.604 | AE7: 265.695 | AF7: 107.627 | AG7: 198.377 | AH7: 444.637 | AI7: 132.338 | AJ7: 27.148 | AK7: 6.421 | AL7: Data unavailable | AM7: 13.612 | AN7: 528.316 | AO7: 104.5 | AP7: =K7+L7 -> 35.178 | AQ7: =J7-AP7 -> 30.264 | AR7: =AB7+AC7 -> 425.577 | AS7: =AR7-V7 -> 412.986 | AT7: =G7+H7+I7+M7 -> 99.294 | AU7: =F7+M7 -> 98.061 | AV7: =E7/D7 -> 0.18643103 | AW7: =E7/AN7 -> 0.30064772 | AX7: =F7/D7 -> 0.075134861 | AY7: =G7/D7 -> 0.050280051 | AZ7: =AQ7/D7 -> 0.035521627 | BA7: =O7/D7 -> 0.0063815453 | BB7: =X7/Z7 -> 3.1699432 | BC7: =AR7/AA7 -> 0.46733579 | BD7: =AJ7-AK7 -> 20.727 | BE7: =F7/I7 -> 4.2261834 | BF7: =AQ7/S7 -> 1.4498419 | BG7: =AQ7/G7 -> 0.70647556 | BH7: =AO7/AN7 -> 0.19779829
A8: H1 2026 | B8: 2026-01-01 | C8: 2026-07-03 | D8: 1163.73 | E8: 186.177 | F8: 79.886 | G8: 58.132 | H8: 7.277 | I8: 15.104 | J8: 70.506 | K8: 29.818 | L8: 1.661 | M8: 37.614 | N8: 5.205 | O8: 8.635 | P8: 12.719 | Q8: 5.926 | R8: 0 | S8: 21.048 | T8: 20.791 | U8: 2.76 | V8: 19.987 | W8: 1870.697 | X8: 869.956 | Y8: 875.83 | Z8: 295.792 | AA8: 994.867 | AB8: 17.478 | AC8: 423.21 | AD8: 442.332 | AE8: 280.186 | AF8: 99.893 | AG8: 260.779 | AH8: 487.444 | AI8: 192.292 | AJ8: 27.148 | AK8: 6.314 | AL8: Data unavailable | AM8: 12.671 | AN8: 569.978 | AO8: 124.8 | AP8: =K8+L8 -> 31.479 | AQ8: =J8-AP8 -> 39.027 | AR8: =AB8+AC8 -> 440.688 | AS8: =AR8-V8 -> 420.701 | AT8: =G8+H8+I8+M8 -> 118.127 | AU8: =F8+M8 -> 117.5 | AV8: =E8/D8 -> 0.15998299 | AW8: =E8/AN8 -> 0.32663892 | AX8: =F8/D8 -> 0.068646507 | AY8: =G8/D8 -> 0.049953168 | AZ8: =AQ8/D8 -> 0.03353613 | BA8: =O8/D8 -> 0.007420106 | BB8: =X8/Z8 -> 2.9411073 | BC8: =AR8/AA8 -> 0.44296172 | BD8: =AJ8-AK8 -> 20.834 | BE8: =F8/I8 -> 5.2890625 | BF8: =AQ8/S8 -> 1.8541904 | BG8: =AQ8/G8 -> 0.67135141 | BH8: =AO8/AN8 -> 0.21895582
A9: TTM | B9: 2025-06-28 | C9: 2026-07-03 | D9: 2098.292 | E9: 335.966 | F9: 125.668 | G9: 90.117 | H9: 6.733 | I9: 30.649 | J9: 108.307 | K9: 58.094 | L9: 17.774 | M9: 72.641 | N9: 10.523 | O9: 14.123 | P9: 25.742 | Q9: 11.731 | R9: 0 | S9: 20.997682 | T9: 20.76134 | U9: 4.29 | V9: 19.987 | W9: 1870.697 | X9: 869.956 | Y9: 875.83 | Z9: 295.792 | AA9: 994.867 | AB9: 17.478 | AC9: 423.21 | AD9: 442.332 | AE9: 280.186 | AF9: 99.893 | AG9: 260.779 | AH9: 487.444 | AI9: 192.292 | AJ9: 27.148 | AK9: 6.314 | AL9: Data unavailable | AM9: 12.671 | AN9: 1087.856 | AO9: 237.2 | AP9: =K9+L9 -> 75.868 | AQ9: =J9-AP9 -> 32.439 | AR9: =AB9+AC9 -> 440.688 | AS9: =AR9-V9 -> 420.701 | AT9: =G9+H9+I9+M9 -> 200.14 | AU9: =F9+M9 -> 198.309 | AV9: =E9/D9 -> 0.16011404 | AW9: =E9/AN9 -> 0.30883315 | AX9: =F9/D9 -> 0.059890616 | AY9: =G9/D9 -> 0.042947788 | AZ9: =AQ9/D9 -> 0.015459717 | BA9: =O9/D9 -> 0.0067307124 | BB9: =X9/Z9 -> 2.9411073 | BC9: =AR9/AA9 -> 0.44296172 | BD9: =AJ9-AK9 -> 20.834 | BE9: =F9/I9 -> 4.1002317 | BF9: =AQ9/S9 -> 1.5448848 | BG9: =AQ9/G9 -> 0.35996538 | BH9: =AO9/AN9 -> 0.21804356

Sheet DCF Downside
A1: Prospective DCF — Downside
A2: FY2026 VA anchor | B2: 1203.1231
A4: Prospective year | B4: 1 | C4: 2 | D4: 3 | E4: 4 | F4: 5
A5: VA sales growth | B5: 0 | C5: 0.03 | D5: 0.04 | E5: 0.04 | F5: 0.04
A6: Value-added sales | B6: =$B$2*(1+B5) -> 1203.1231 | C6: =B6*(1+C5) -> 1239.2168 | D6: =C6*(1+D5) -> 1288.7855 | E6: =D6*(1+E5) -> 1340.3369 | F6: =E6*(1+F5) -> 1393.9504
A7: EBITDA / VA sales | B7: 0.205 | C7: 0.21 | D7: 0.215 | E7: 0.22 | F7: 0.22
A8: EBITDA | B8: =B6*B7 -> 246.64024 | C8: =C6*C7 -> 260.23553 | D8: =D6*D7 -> 277.08887 | E8: =E6*E7 -> 294.87411 | F8: =F6*F7 -> 306.66908
A9: D&A / VA sales | B9: 0.067 | C9: 0.067 | D9: 0.067 | E9: 0.067 | F9: 0.067
A10: D&A | B10: =B6*B9 -> 80.609248 | C10: =C6*C9 -> 83.027525 | D10: =D6*D9 -> 86.348626 | E10: =E6*E9 -> 89.802571 | F10: =F6*F9 -> 93.394674
A11: EBIT | B11: =B8-B10 -> 166.03099 | C11: =C8-C10 -> 177.208 | D11: =D8-D10 -> 190.74025 | E11: =E8-E10 -> 205.07154 | F11: =F8-F10 -> 213.2744
A12: Tax rate | B12: 0.18 | C12: 0.19 | D12: 0.2 | E12: 0.21 | F12: 0.21
A13: NOPAT | B13: =B11*(1-B12) -> 136.14541 | C13: =C11*(1-C12) -> 143.53848 | D13: =D11*(1-D12) -> 152.5922 | E13: =E11*(1-E12) -> 162.00652 | F13: =F11*(1-F12) -> 168.48678
A14: Capex / VA sales | B14: 0.085 | C14: 0.085 | D14: 0.085 | E14: 0.085 | F14: 0.085
A15: Capex incl. mining | B15: =B6*B14 -> 102.26546 | C15: =C6*C14 -> 105.33343 | D15: =D6*D14 -> 109.54676 | E15: =E6*E14 -> 113.92864 | F15: =F6*F14 -> 118.48578
A16: NWC / incremental VA | B16: 0.35 | C16: 0.35 | D16: 0.35 | E16: 0.35 | F16: 0.35
A17: Change in NWC | B17: =(B6-$B$2)*B16 -> 0 | C17: =(C6-B6)*C16 -> 12.632793 | D17: =(D6-C6)*D16 -> 17.349035 | E17: =(E6-D6)*E16 -> 18.042997 | F17: =(F6-E6)*F16 -> 18.764716
A18: FCFF | B18: =B13+B10-B15-B17 -> 114.48919 | C18: =C13+C10-C15-C17 -> 108.59979 | D18: =D13+D10-D15-D17 -> 112.04503 | E18: =E13+E10-E15-E17 -> 119.83746 | F18: =F13+F10-F15-F17 -> 124.63096
A19: Present value of FCFF | B19: =B18/(1+$B$21)^B4 -> 102.22249 | C19: =C18/(1+$B$21)^C4 -> 86.575085 | D19: =D18/(1+$B$21)^D4 -> 79.751436 | E19: =E18/(1+$B$21)^E4 -> 76.158871 | F19: =F18/(1+$B$21)^F4 -> 70.718952
A21: WACC | B21: 0.12
A22: Terminal growth | B22: 0.02
A23: Diluted shares | B23: 21.15
A24: Net claims | B24: 458.8
A26: Terminal VA sales | B26: =F6*(1+B22) -> 1421.8294
A27: Terminal EBITDA | B27: =B26*F7 -> 312.80246
A28: Terminal D&A | B28: =B26*F9 -> 95.262568
A29: Terminal EBIT | B29: =B27-B28 -> 217.53989
A30: Terminal capex | B30: =B26*F14 -> 120.8555
A31: Terminal change NWC | B31: =F6*B22*F16 -> 9.7576525
A32: Terminal FCFF | B32: =B29*(1-F12)+B28-B30-B31 -> 136.50593
A33: Terminal value | B33: =B32/(B21-B22) -> 1365.0593
A34: PV of terminal value | B34: =B33/(1+B21)^F4 -> 774.57133
A35: PV explicit cash flows | B35: =SUM(B19:F19) -> 415.42684
A36: Enterprise value | B36: =B34+B35 -> 1189.9982
A37: Equity value | B37: =B36-B24 -> 731.19817
A38: Per-share value | B38: =B37/B23 -> 34.572018
A39: Terminal share of EV | B39: =B34/B36 -> 0.65090128
A41: Terminal capex and working capital are recalculated at terminal growth; SBC remains an expense.

Sheet DCF Base
A1: Prospective DCF — Base
A2: FY2026 VA anchor | B2: 1203.1231
A4: Prospective year | B4: 1 | C4: 2 | D4: 3 | E4: 4 | F4: 5
A5: VA sales growth | B5: 0.075 | C5: 0.12 | D5: 0.1 | E5: 0.08 | F5: 0.06
A6: Value-added sales | B6: =$B$2*(1+B5) -> 1293.3573 | C6: =B6*(1+C5) -> 1448.5602 | D6: =C6*(1+D5) -> 1593.4162 | E6: =D6*(1+E5) -> 1720.8895 | F6: =E6*(1+F5) -> 1824.1429
A7: EBITDA / VA sales | B7: 0.235 | C7: 0.24 | D7: 0.245 | E7: 0.25 | F7: 0.25
A8: EBITDA | B8: =B6*B7 -> 303.93897 | C8: =C6*C7 -> 347.65445 | D8: =D6*D7 -> 390.38698 | E8: =E6*E7 -> 430.22238 | F8: =F6*F7 -> 456.03573
A9: D&A / VA sales | B9: 0.062 | C9: 0.062 | D9: 0.062 | E9: 0.062 | F9: 0.062
A10: D&A | B10: =B6*B9 -> 80.188155 | C10: =C6*C9 -> 89.810733 | D10: =D6*D9 -> 98.791806 | E10: =E6*E9 -> 106.69515 | F10: =F6*F9 -> 113.09686
A11: EBIT | B11: =B8-B10 -> 223.75082 | C11: =C8-C10 -> 257.84372 | D11: =D8-D10 -> 291.59517 | E11: =E8-E10 -> 323.52723 | F11: =F8-F10 -> 342.93887
A12: Tax rate | B12: 0.17 | C12: 0.18 | D12: 0.19 | E12: 0.2 | F12: 0.2
A13: NOPAT | B13: =B11*(1-B12) -> 185.71318 | C13: =C11*(1-C12) -> 211.43185 | D13: =D11*(1-D12) -> 236.19209 | E13: =E11*(1-E12) -> 258.82179 | F13: =F11*(1-F12) -> 274.35109
A14: Capex / VA sales | B14: 0.078 | C14: 0.078 | D14: 0.078 | E14: 0.078 | F14: 0.078
A15: Capex incl. mining | B15: =B6*B14 -> 100.88187 | C15: =C6*C14 -> 112.9877 | D15: =D6*D14 -> 124.28647 | E15: =E6*E14 -> 134.22938 | F15: =F6*F14 -> 142.28315
A16: NWC / incremental VA | B16: 0.3 | C16: 0.3 | D16: 0.3 | E16: 0.3 | F16: 0.3
A17: Change in NWC | B17: =(B6-$B$2)*B16 -> 27.07027 | C17: =(C6-B6)*C16 -> 46.560864 | D17: =(D6-C6)*D16 -> 43.456806 | E17: =(E6-D6)*E16 -> 38.24199 | F17: =(F6-E6)*F16 -> 30.976012
A18: FCFF | B18: =B13+B10-B15-B17 -> 137.94919 | C18: =C13+C10-C15-C17 -> 141.69402 | D18: =D13+D10-D15-D17 -> 167.24062 | E18: =E13+E10-E15-E17 -> 193.04556 | F18: =F13+F10-F15-F17 -> 214.18879
A19: Present value of FCFF | B19: =B18/(1+$B$21)^B4 -> 124.8409 | C19: =C18/(1+$B$21)^C4 -> 116.04514 | D19: =D18/(1+$B$21)^D4 -> 123.9524 | E19: =E18/(1+$B$21)^E4 -> 129.48239 | F19: =F18/(1+$B$21)^F4 -> 130.01257
A21: WACC | B21: 0.105
A22: Terminal growth | B22: 0.03
A23: Diluted shares | B23: 21.15
A24: Net claims | B24: 458.8
A26: Terminal VA sales | B26: =F6*(1+B22) -> 1878.8672
A27: Terminal EBITDA | B27: =B26*F7 -> 469.7168
A28: Terminal D&A | B28: =B26*F9 -> 116.48977
A29: Terminal EBIT | B29: =B27-B28 -> 353.22703
A30: Terminal capex | B30: =B26*F14 -> 146.55164
A31: Terminal change NWC | B31: =F6*B22*F16 -> 16.417286
A32: Terminal FCFF | B32: =B29*(1-F12)+B28-B30-B31 -> 236.10246
A33: Terminal value | B33: =B32/(B21-B22) -> 3148.0329
A34: PV of terminal value | B34: =B33/(1+B21)^F4 -> 1910.8556
A35: PV explicit cash flows | B35: =SUM(B19:F19) -> 624.33341
A36: Enterprise value | B36: =B34+B35 -> 2535.189
A37: Equity value | B37: =B36-B24 -> 2076.389
A38: Per-share value | B38: =B37/B23 -> 98.174421
A39: Terminal share of EV | B39: =B34/B36 -> 0.75373299
A41: Terminal capex and working capital are recalculated at terminal growth; SBC remains an expense.

Sheet DCF Upside
A1: Prospective DCF — Upside
A2: FY2026 VA anchor | B2: 1203.1231
A4: Prospective year | B4: 1 | C4: 2 | D4: 3 | E4: 4 | F4: 5
A5: VA sales growth | B5: 0.15 | C5: 0.2 | D5: 0.18 | E5: 0.15 | F5: 0.12
A6: Value-added sales | B6: =$B$2*(1+B5) -> 1383.5916 | C6: =B6*(1+C5) -> 1660.3099 | D6: =C6*(1+D5) -> 1959.1657 | E6: =D6*(1+E5) -> 2253.0405 | F6: =E6*(1+F5) -> 2523.4054
A7: EBITDA / VA sales | B7: 0.25 | C7: 0.265 | D7: 0.275 | E7: 0.28 | F7: 0.28
A8: EBITDA | B8: =B6*B7 -> 345.89789 | C8: =C6*C7 -> 439.98212 | D8: =D6*D7 -> 538.77056 | E8: =E6*E7 -> 630.85134 | F8: =F6*F7 -> 706.5535
A9: D&A / VA sales | B9: 0.06 | C9: 0.06 | D9: 0.06 | E9: 0.06 | F9: 0.06
A10: D&A | B10: =B6*B9 -> 83.015494 | C10: =C6*C9 -> 99.618593 | D10: =D6*D9 -> 117.54994 | E10: =E6*E9 -> 135.18243 | F10: =F6*F9 -> 151.40432
A11: EBIT | B11: =B8-B10 -> 262.8824 | C11: =C8-C10 -> 340.36352 | D11: =D8-D10 -> 421.22062 | E11: =E8-E10 -> 495.66891 | F11: =F8-F10 -> 555.14918
A12: Tax rate | B12: 0.16 | C12: 0.17 | D12: 0.18 | E12: 0.18 | F12: 0.18
A13: NOPAT | B13: =B11*(1-B12) -> 220.82121 | C13: =C11*(1-C12) -> 282.50173 | D13: =D11*(1-D12) -> 345.40091 | E13: =E11*(1-E12) -> 406.44851 | F13: =F11*(1-F12) -> 455.22233
A14: Capex / VA sales | B14: 0.08 | C14: 0.08 | D14: 0.08 | E14: 0.08 | F14: 0.08
A15: Capex incl. mining | B15: =B6*B14 -> 110.68733 | C15: =C6*C14 -> 132.82479 | D15: =D6*D14 -> 156.73325 | E15: =E6*E14 -> 180.24324 | F15: =F6*F14 -> 201.87243
A16: NWC / incremental VA | B16: 0.28 | C16: 0.28 | D16: 0.28 | E16: 0.28 | F16: 0.28
A17: Change in NWC | B17: =(B6-$B$2)*B16 -> 50.53117 | C17: =(C6-B6)*C16 -> 77.481128 | D17: =(D6-C6)*D16 -> 83.679618 | E17: =(E6-D6)*E16 -> 82.284958 | F17: =(F6-E6)*F16 -> 75.702161
A18: FCFF | B18: =B13+B10-B15-B17 -> 142.61821 | C18: =C13+C10-C15-C17 -> 171.8144 | D18: =D13+D10-D15-D17 -> 222.53797 | E18: =E13+E10-E15-E17 -> 279.10274 | F18: =F13+F10-F15-F17 -> 329.05206
A19: Present value of FCFF | B19: =B18/(1+$B$21)^B4 -> 130.24494 | C19: =C18/(1+$B$21)^C4 -> 143.29509 | D19: =D18/(1+$B$21)^D4 -> 169.49691 | E19: =E18/(1+$B$21)^E4 -> 194.13669 | F19: =F18/(1+$B$21)^F4 -> 209.02297
A21: WACC | B21: 0.095
A22: Terminal growth | B22: 0.035
A23: Diluted shares | B23: 21.15
A24: Net claims | B24: 458.8
A26: Terminal VA sales | B26: =F6*(1+B22) -> 2611.7246
A27: Terminal EBITDA | B27: =B26*F7 -> 731.28287
A28: Terminal D&A | B28: =B26*F9 -> 156.70347
A29: Terminal EBIT | B29: =B27-B28 -> 574.5794
A30: Terminal capex | B30: =B26*F14 -> 208.93796
A31: Terminal change NWC | B31: =F6*B22*F16 -> 24.729373
A32: Terminal FCFF | B32: =B29*(1-F12)+B28-B30-B31 -> 394.19125
A33: Terminal value | B33: =B32/(B21-B22) -> 6569.8541
A34: PV of terminal value | B34: =B33/(1+B21)^F4 -> 4173.3531
A35: PV explicit cash flows | B35: =SUM(B19:F19) -> 846.1966
A36: Enterprise value | B36: =B34+B35 -> 5019.5497
A37: Equity value | B37: =B36-B24 -> 4560.7497
A38: Per-share value | B38: =B37/B23 -> 215.63828
A39: Terminal share of EV | B39: =B34/B36 -> 0.83141982
A41: Terminal capex and working capital are recalculated at terminal growth; SBC remains an expense.

Sheet DCF summary
A1: scenario | B1: pv_explicit | C1: pv_terminal | D1: enterprise | E1: equity | F1: per_share | G1: terminal_share | H1: terminal_fcff | I1: wacc | J1: g | K1: return_vs_price | L1: initial_va
A2: Downside | B2: ='DCF Downside'!B35 -> 415.42684 | C2: ='DCF Downside'!B34 -> 774.57133 | D2: ='DCF Downside'!B36 -> 1189.9982 | E2: ='DCF Downside'!B37 -> 731.19817 | F2: ='DCF Downside'!B38 -> 34.572018 | G2: 0.65090128 | H2: 136.50593 | I2: 0.12 | J2: 0.02 | K2: -0.8625531 | L2: 1203.1231
A3: Base | B3: ='DCF Base'!B35 -> 624.33341 | C3: ='DCF Base'!B34 -> 1910.8556 | D3: ='DCF Base'!B36 -> 2535.189 | E3: ='DCF Base'!B37 -> 2076.389 | F3: ='DCF Base'!B38 -> 98.174421 | G3: 0.75373299 | H3: 236.10246 | I3: 0.105 | J3: 0.03 | K3: -0.60969101 | L3: 1203.1231
A4: Upside | B4: ='DCF Upside'!B35 -> 846.1966 | C4: ='DCF Upside'!B34 -> 4173.3531 | D4: ='DCF Upside'!B36 -> 5019.5497 | E4: ='DCF Upside'!B37 -> 4560.7497 | F4: ='DCF Upside'!B38 -> 215.63828 | G4: 0.83141982 | H4: 394.19125 | I4: 0.095 | J4: 0.035 | K4: -0.14269358 | L4: 1203.1231

Sheet Sensitivity
A1: WACC / terminal g | B1: 0.02 | C1: 0.025 | D1: 0.03 | E1: 0.035 | F1: 0.04
A2: 0.085 | B2: =('DCF Base'!B18/(1+$A2)^1+'DCF Base'!C18/(1+$A2)^2+'DCF Base'!D18/(1+$A2)^3+'DCF Base'!E18/(1+$A2)^4+'DCF Base'!F18/(1+$A2)^5+('DCF Base'!F6*(1+B$1)*(('DCF Base'!F7-'DCF Base'!F9)*(1-'DCF Base'!F12)+'DCF Base'!F9-'DCF Base'!F14)-'DCF Base'!F6*B$1*'DCF Base'!F16)/($A2-B$1)/(1+$A2)^5-'DCF Base'!B24)/'DCF Base'!B23 -> 125.19918 | C2: =('DCF Base'!B18/(1+$A2)^1+'DCF Base'!C18/(1+$A2)^2+'DCF Base'!D18/(1+$A2)^3+'DCF Base'!E18/(1+$A2)^4+'DCF Base'!F18/(1+$A2)^5+('DCF Base'!F6*(1+C$1)*(('DCF Base'!F7-'DCF Base'!F9)*(1-'DCF Base'!F12)+'DCF Base'!F9-'DCF Base'!F14)-'DCF Base'!F6*C$1*'DCF Base'!F16)/($A2-C$1)/(1+$A2)^5-'DCF Base'!B24)/'DCF Base'!B23 -> 134.04743 | D2: =('DCF Base'!B18/(1+$A2)^1+'DCF Base'!C18/(1+$A2)^2+'DCF Base'!D18/(1+$A2)^3+'DCF Base'!E18/(1+$A2)^4+'DCF Base'!F18/(1+$A2)^5+('DCF Base'!F6*(1+D$1)*(('DCF Base'!F7-'DCF Base'!F9)*(1-'DCF Base'!F12)+'DCF Base'!F9-'DCF Base'!F14)-'DCF Base'!F6*D$1*'DCF Base'!F16)/($A2-D$1)/(1+$A2)^5-'DCF Base'!B24)/'DCF Base'!B23 -> 144.50446 | E2: =('DCF Base'!B18/(1+$A2)^1+'DCF Base'!C18/(1+$A2)^2+'DCF Base'!D18/(1+$A2)^3+'DCF Base'!E18/(1+$A2)^4+'DCF Base'!F18/(1+$A2)^5+('DCF Base'!F6*(1+E$1)*(('DCF Base'!F7-'DCF Base'!F9)*(1-'DCF Base'!F12)+'DCF Base'!F9-'DCF Base'!F14)-'DCF Base'!F6*E$1*'DCF Base'!F16)/($A2-E$1)/(1+$A2)^5-'DCF Base'!B24)/'DCF Base'!B23 -> 157.05289 | F2: =('DCF Base'!B18/(1+$A2)^1+'DCF Base'!C18/(1+$A2)^2+'DCF Base'!D18/(1+$A2)^3+'DCF Base'!E18/(1+$A2)^4+'DCF Base'!F18/(1+$A2)^5+('DCF Base'!F6*(1+F$1)*(('DCF Base'!F7-'DCF Base'!F9)*(1-'DCF Base'!F12)+'DCF Base'!F9-'DCF Base'!F14)-'DCF Base'!F6*F$1*'DCF Base'!F16)/($A2-F$1)/(1+$A2)^5-'DCF Base'!B24)/'DCF Base'!B23 -> 172.38986
A3: 0.095 | B3: =('DCF Base'!B18/(1+$A3)^1+'DCF Base'!C18/(1+$A3)^2+'DCF Base'!D18/(1+$A3)^3+'DCF Base'!E18/(1+$A3)^4+'DCF Base'!F18/(1+$A3)^5+('DCF Base'!F6*(1+B$1)*(('DCF Base'!F7-'DCF Base'!F9)*(1-'DCF Base'!F12)+'DCF Base'!F9-'DCF Base'!F14)-'DCF Base'!F6*B$1*'DCF Base'!F16)/($A3-B$1)/(1+$A3)^5-'DCF Base'!B24)/'DCF Base'!B23 -> 104.41483 | C3: =('DCF Base'!B18/(1+$A3)^1+'DCF Base'!C18/(1+$A3)^2+'DCF Base'!D18/(1+$A3)^3+'DCF Base'!E18/(1+$A3)^4+'DCF Base'!F18/(1+$A3)^5+('DCF Base'!F6*(1+C$1)*(('DCF Base'!F7-'DCF Base'!F9)*(1-'DCF Base'!F12)+'DCF Base'!F9-'DCF Base'!F14)-'DCF Base'!F6*C$1*'DCF Base'!F16)/($A3-C$1)/(1+$A3)^5-'DCF Base'!B24)/'DCF Base'!B23 -> 110.60671 | D3: =('DCF Base'!B18/(1+$A3)^1+'DCF Base'!C18/(1+$A3)^2+'DCF Base'!D18/(1+$A3)^3+'DCF Base'!E18/(1+$A3)^4+'DCF Base'!F18/(1+$A3)^5+('DCF Base'!F6*(1+D$1)*(('DCF Base'!F7-'DCF Base'!F9)*(1-'DCF Base'!F12)+'DCF Base'!F9-'DCF Base'!F14)-'DCF Base'!F6*D$1*'DCF Base'!F16)/($A3-D$1)/(1+$A3)^5-'DCF Base'!B24)/'DCF Base'!B23 -> 117.75118 | E3: =('DCF Base'!B18/(1+$A3)^1+'DCF Base'!C18/(1+$A3)^2+'DCF Base'!D18/(1+$A3)^3+'DCF Base'!E18/(1+$A3)^4+'DCF Base'!F18/(1+$A3)^5+('DCF Base'!F6*(1+E$1)*(('DCF Base'!F7-'DCF Base'!F9)*(1-'DCF Base'!F12)+'DCF Base'!F9-'DCF Base'!F14)-'DCF Base'!F6*E$1*'DCF Base'!F16)/($A3-E$1)/(1+$A3)^5-'DCF Base'!B24)/'DCF Base'!B23 -> 126.0864 | F3: =('DCF Base'!B18/(1+$A3)^1+'DCF Base'!C18/(1+$A3)^2+'DCF Base'!D18/(1+$A3)^3+'DCF Base'!E18/(1+$A3)^4+'DCF Base'!F18/(1+$A3)^5+('DCF Base'!F6*(1+F$1)*(('DCF Base'!F7-'DCF Base'!F9)*(1-'DCF Base'!F12)+'DCF Base'!F9-'DCF Base'!F14)-'DCF Base'!F6*F$1*'DCF Base'!F16)/($A3-F$1)/(1+$A3)^5-'DCF Base'!B24)/'DCF Base'!B23 -> 135.93711
A4: 0.105 | B4: =('DCF Base'!B18/(1+$A4)^1+'DCF Base'!C18/(1+$A4)^2+'DCF Base'!D18/(1+$A4)^3+'DCF Base'!E18/(1+$A4)^4+'DCF Base'!F18/(1+$A4)^5+('DCF Base'!F6*(1+B$1)*(('DCF Base'!F7-'DCF Base'!F9)*(1-'DCF Base'!F12)+'DCF Base'!F9-'DCF Base'!F14)-'DCF Base'!F6*B$1*'DCF Base'!F16)/($A4-B$1)/(1+$A4)^5-'DCF Base'!B24)/'DCF Base'!B23 -> 88.565219 | C4: =('DCF Base'!B18/(1+$A4)^1+'DCF Base'!C18/(1+$A4)^2+'DCF Base'!D18/(1+$A4)^3+'DCF Base'!E18/(1+$A4)^4+'DCF Base'!F18/(1+$A4)^5+('DCF Base'!F6*(1+C$1)*(('DCF Base'!F7-'DCF Base'!F9)*(1-'DCF Base'!F12)+'DCF Base'!F9-'DCF Base'!F14)-'DCF Base'!F6*C$1*'DCF Base'!F16)/($A4-C$1)/(1+$A4)^5-'DCF Base'!B24)/'DCF Base'!B23 -> 93.069532 | D4: =('DCF Base'!B18/(1+$A4)^1+'DCF Base'!C18/(1+$A4)^2+'DCF Base'!D18/(1+$A4)^3+'DCF Base'!E18/(1+$A4)^4+'DCF Base'!F18/(1+$A4)^5+('DCF Base'!F6*(1+D$1)*(('DCF Base'!F7-'DCF Base'!F9)*(1-'DCF Base'!F12)+'DCF Base'!F9-'DCF Base'!F14)-'DCF Base'!F6*D$1*'DCF Base'!F16)/($A4-D$1)/(1+$A4)^5-'DCF Base'!B24)/'DCF Base'!B23 -> 98.174421 | E4: =('DCF Base'!B18/(1+$A4)^1+'DCF Base'!C18/(1+$A4)^2+'DCF Base'!D18/(1+$A4)^3+'DCF Base'!E18/(1+$A4)^4+'DCF Base'!F18/(1+$A4)^5+('DCF Base'!F6*(1+E$1)*(('DCF Base'!F7-'DCF Base'!F9)*(1-'DCF Base'!F12)+'DCF Base'!F9-'DCF Base'!F14)-'DCF Base'!F6*E$1*'DCF Base'!F16)/($A4-E$1)/(1+$A4)^5-'DCF Base'!B24)/'DCF Base'!B23 -> 104.00858 | F4: =('DCF Base'!B18/(1+$A4)^1+'DCF Base'!C18/(1+$A4)^2+'DCF Base'!D18/(1+$A4)^3+'DCF Base'!E18/(1+$A4)^4+'DCF Base'!F18/(1+$A4)^5+('DCF Base'!F6*(1+F$1)*(('DCF Base'!F7-'DCF Base'!F9)*(1-'DCF Base'!F12)+'DCF Base'!F9-'DCF Base'!F14)-'DCF Base'!F6*F$1*'DCF Base'!F16)/($A4-F$1)/(1+$A4)^5-'DCF Base'!B24)/'DCF Base'!B23 -> 110.7403
A5: 0.115 | B5: =('DCF Base'!B18/(1+$A5)^1+'DCF Base'!C18/(1+$A5)^2+'DCF Base'!D18/(1+$A5)^3+'DCF Base'!E18/(1+$A5)^4+'DCF Base'!F18/(1+$A5)^5+('DCF Base'!F6*(1+B$1)*(('DCF Base'!F7-'DCF Base'!F9)*(1-'DCF Base'!F12)+'DCF Base'!F9-'DCF Base'!F14)-'DCF Base'!F6*B$1*'DCF Base'!F16)/($A5-B$1)/(1+$A5)^5-'DCF Base'!B24)/'DCF Base'!B23 -> 76.08992 | C5: =('DCF Base'!B18/(1+$A5)^1+'DCF Base'!C18/(1+$A5)^2+'DCF Base'!D18/(1+$A5)^3+'DCF Base'!E18/(1+$A5)^4+'DCF Base'!F18/(1+$A5)^5+('DCF Base'!F6*(1+C$1)*(('DCF Base'!F7-'DCF Base'!F9)*(1-'DCF Base'!F12)+'DCF Base'!F9-'DCF Base'!F14)-'DCF Base'!F6*C$1*'DCF Base'!F16)/($A5-C$1)/(1+$A5)^5-'DCF Base'!B24)/'DCF Base'!B23 -> 79.466043 | D5: =('DCF Base'!B18/(1+$A5)^1+'DCF Base'!C18/(1+$A5)^2+'DCF Base'!D18/(1+$A5)^3+'DCF Base'!E18/(1+$A5)^4+'DCF Base'!F18/(1+$A5)^5+('DCF Base'!F6*(1+D$1)*(('DCF Base'!F7-'DCF Base'!F9)*(1-'DCF Base'!F12)+'DCF Base'!F9-'DCF Base'!F14)-'DCF Base'!F6*D$1*'DCF Base'!F16)/($A5-D$1)/(1+$A5)^5-'DCF Base'!B24)/'DCF Base'!B23 -> 83.239356 | E5: =('DCF Base'!B18/(1+$A5)^1+'DCF Base'!C18/(1+$A5)^2+'DCF Base'!D18/(1+$A5)^3+'DCF Base'!E18/(1+$A5)^4+'DCF Base'!F18/(1+$A5)^5+('DCF Base'!F6*(1+E$1)*(('DCF Base'!F7-'DCF Base'!F9)*(1-'DCF Base'!F12)+'DCF Base'!F9-'DCF Base'!F14)-'DCF Base'!F6*E$1*'DCF Base'!F16)/($A5-E$1)/(1+$A5)^5-'DCF Base'!B24)/'DCF Base'!B23 -> 87.484334 | F5: =('DCF Base'!B18/(1+$A5)^1+'DCF Base'!C18/(1+$A5)^2+'DCF Base'!D18/(1+$A5)^3+'DCF Base'!E18/(1+$A5)^4+'DCF Base'!F18/(1+$A5)^5+('DCF Base'!F6*(1+F$1)*(('DCF Base'!F7-'DCF Base'!F9)*(1-'DCF Base'!F12)+'DCF Base'!F9-'DCF Base'!F14)-'DCF Base'!F6*F$1*'DCF Base'!F16)/($A5-F$1)/(1+$A5)^5-'DCF Base'!B24)/'DCF Base'!B23 -> 92.295309
A6: 0.125 | B6: =('DCF Base'!B18/(1+$A6)^1+'DCF Base'!C18/(1+$A6)^2+'DCF Base'!D18/(1+$A6)^3+'DCF Base'!E18/(1+$A6)^4+'DCF Base'!F18/(1+$A6)^5+('DCF Base'!F6*(1+B$1)*(('DCF Base'!F7-'DCF Base'!F9)*(1-'DCF Base'!F12)+'DCF Base'!F9-'DCF Base'!F14)-'DCF Base'!F6*B$1*'DCF Base'!F16)/($A6-B$1)/(1+$A6)^5-'DCF Base'!B24)/'DCF Base'!B23 -> 66.023075 | C6: =('DCF Base'!B18/(1+$A6)^1+'DCF Base'!C18/(1+$A6)^2+'DCF Base'!D18/(1+$A6)^3+'DCF Base'!E18/(1+$A6)^4+'DCF Base'!F18/(1+$A6)^5+('DCF Base'!F6*(1+C$1)*(('DCF Base'!F7-'DCF Base'!F9)*(1-'DCF Base'!F12)+'DCF Base'!F9-'DCF Base'!F14)-'DCF Base'!F6*C$1*'DCF Base'!F16)/($A6-C$1)/(1+$A6)^5-'DCF Base'!B24)/'DCF Base'!B23 -> 68.61443 | D6: =('DCF Base'!B18/(1+$A6)^1+'DCF Base'!C18/(1+$A6)^2+'DCF Base'!D18/(1+$A6)^3+'DCF Base'!E18/(1+$A6)^4+'DCF Base'!F18/(1+$A6)^5+('DCF Base'!F6*(1+D$1)*(('DCF Base'!F7-'DCF Base'!F9)*(1-'DCF Base'!F12)+'DCF Base'!F9-'DCF Base'!F14)-'DCF Base'!F6*D$1*'DCF Base'!F16)/($A6-D$1)/(1+$A6)^5-'DCF Base'!B24)/'DCF Base'!B23 -> 71.478561 | E6: =('DCF Base'!B18/(1+$A6)^1+'DCF Base'!C18/(1+$A6)^2+'DCF Base'!D18/(1+$A6)^3+'DCF Base'!E18/(1+$A6)^4+'DCF Base'!F18/(1+$A6)^5+('DCF Base'!F6*(1+E$1)*(('DCF Base'!F7-'DCF Base'!F9)*(1-'DCF Base'!F12)+'DCF Base'!F9-'DCF Base'!F14)-'DCF Base'!F6*E$1*'DCF Base'!F16)/($A6-E$1)/(1+$A6)^5-'DCF Base'!B24)/'DCF Base'!B23 -> 74.660927 | F6: =('DCF Base'!B18/(1+$A6)^1+'DCF Base'!C18/(1+$A6)^2+'DCF Base'!D18/(1+$A6)^3+'DCF Base'!E18/(1+$A6)^4+'DCF Base'!F18/(1+$A6)^5+('DCF Base'!F6*(1+F$1)*(('DCF Base'!F7-'DCF Base'!F9)*(1-'DCF Base'!F12)+'DCF Base'!F9-'DCF Base'!F14)-'DCF Base'!F6*F$1*'DCF Base'!F16)/($A6-F$1)/(1+$A6)^5-'DCF Base'!B24)/'DCF Base'!B23 -> 78.21769

Sheet Earnings scenarios
A1: scenario | B1: fy2026_va_anchor | C1: fy2027_va | D1: growth | E1: gross_margin_va | F1: gross_profit | G1: revenue | H1: gross_margin_gaap | I1: ebitda_margin_va | J1: ebitda | K1: da | L1: ebit | M1: operating_margin_gaap | N1: tax | O1: interest | P1: acquisition_amortization_addback | Q1: adjusted_net_income | R1: eps | S1: capex | T1: nwc_ratio | U1: change_nwc | V1: fcff | W1: normalized_equity_fcf | X1: assumed_pe | Y1: price | Z1: price_return
A2: Downside | B2: 1203.1231 | C2: =B2*(1+D2) -> 1203.1231 | D2: 0 | E2: 0.31 | F2: =C2*E2 -> 372.96816 | G2: =C2/0.55 -> 2187.4965 | H2: =E2*0.55 -> 0.1705 | I2: 0.2 | J2: =C2*I2 -> 240.62462 | K2: 80 | L2: =J2-K2 -> 160.62462 | M2: =L2/G2 -> 0.073428514 | N2: 0.18 | O2: 30 | P2: 10 | Q2: =(L2+P2-O2)*(1-N2) -> 115.31219 | R2: =Q2/21.15 -> 5.4521129 | S2: 100 | T2: 0.3 | U2: =(C2-B2)*T2 -> 0 | V2: =L2*(1-N2)+K2-S2-U2 -> 111.71219 | W2: =V2-O2*(1-N2) -> 87.112188 | X2: 20 | Y2: =R2*X2 -> 109.04226 | Z2: =Y2/251.53-1 -> -0.56648408
A3: Base | B3: 1203.1231 | C3: =B3*(1+D3) -> 1323.4354 | D3: 0.1 | E3: 0.36 | F3: =C3*E3 -> 476.43675 | G3: =C3/0.55 -> 2406.2462 | H3: =E3*0.55 -> 0.198 | I3: 0.24 | J3: =C3*I3 -> 317.6245 | K3: 82 | L3: =J3-K3 -> 235.6245 | M3: =L3/G3 -> 0.097922024 | N3: 0.17 | O3: 28 | P3: 10 | Q3: =(L3+P3-O3)*(1-N3) -> 180.62833 | R3: =Q3/21.15 -> 8.5403467 | S3: 110 | T3: 0.3 | U3: =(C3-B3)*T3 -> 36.093693 | V3: =L3*(1-N3)+K3-S3-U3 -> 131.47464 | W3: =V3-O3*(1-N3) -> 108.23464 | X3: 24 | Y3: =R3*X3 -> 204.96832 | Z3: =Y3/251.53-1 -> -0.18511382
A4: Upside | B4: 1203.1231 | C4: =B4*(1+D4) -> 1467.8102 | D4: 0.22 | E4: 0.4 | F4: =C4*E4 -> 587.12407 | G4: =C4/0.55 -> 2668.7458 | H4: =E4*0.55 -> 0.22 | I4: 0.27 | J4: =C4*I4 -> 396.30875 | K4: 88 | L4: =J4-K4 -> 308.30875 | M4: =L4/G4 -> 0.11552571 | N4: 0.16 | O4: 26 | P4: 10 | Q4: =(L4+P4-O4)*(1-N4) -> 245.53935 | R4: =Q4/21.15 -> 11.609425 | S4: 150 | T4: 0.28 | U4: =(C4-B4)*T4 -> 74.112383 | V4: =L4*(1-N4)+K4-S4-U4 -> 122.86697 | W4: =V4-O4*(1-N4) -> 101.02697 | X4: 28 | Y4: =R4*X4 -> 325.06391 | Z4: =Y4/251.53-1 -> 0.2923465

Sheet Peers
A1: ticker | B1: period_end | C1: revenue | D1: net_income | E1: operating_income | F1: gross_profit | G1: cfo | H1: capex | I1: cash | J1: debt | K1: equity | L1: da | M1: ebitda_operating | N1: adjusted_ebitda | O1: shares | P1: price | Q1: market_cap_diluted | R1: ev | S1: fcf | T1: net_debt | U1: pe | V1: ps | W1: pb | X1: ev_revenue | Y1: ev_ebitda_operating | Z1: ev_adjusted_ebitda | AA1: fcf_yield | AB1: operating_margin | AC1: gross_margin
A2: ENTG | B2: 2026-06-27 | C2: 3326.1 | D2: 305.5 | E2: 533.7 | F2: 1512.7 | G2: 780.7 | H2: 205.5 | I2: 353.6 | J2: 3456 | K2: 4156.2 | L2: 357.3 | M2: 891 | N2: 925.6 | O2: 153.4 | P2: 142.25 | Q2: 21821.15 | R2: 24923.55 | S2: 575.2 | T2: 3102.4 | U2: 71.42766 | V2: 6.5605815 | W2: 5.2502647 | X2: 7.4933255 | Y2: 27.972559 | Z2: 26.926912 | AA2: 0.026359747 | AB2: 0.16045819 | AC2: 0.45479691
A3: CRS | B3: 2026-06-30 | C3: 3124.2 | D3: 529.8 | E3: 702 | F3: 955.5 | G3: 605 | H3: 242.7 | I3: 393.3 | J3: 690.7 | K3: 2227.6 | L3: 147.1 | M3: 849.1 | N3: Data unavailable | O3: 50.4 | P3: 408.12 | Q3: 20569.248 | R3: 20866.648 | S3: 362.3 | T3: 297.4 | U3: 38.824552 | V3: 6.5838447 | W3: 9.2338157 | X3: 6.6790371 | Y3: 24.575018 | Z3: Data unavailable | AA3: 0.017613673 | AB3: 0.22469752 | AC3: 0.30583829
A4: ATI | B4: 2026-06-28 | C4: 4715.2 | D4: 475.8 | E4: 716.8 | F4: 1101.4 | G4: 805.3 | H4: 279 | I4: 783 | J4: 2192 | K4: 1876.7 | L4: 174.7 | M4: 891.5 | N4: Data unavailable | O4: 138.5 | P4: 191.63 | Q4: 26540.756 | R4: 27949.756 | S4: 526.3 | T4: 1409 | U4: 55.781328 | V4: 5.6287656 | W4: 14.142247 | X4: 5.9275865 | Y4: 31.35138 | Z4: Data unavailable | AA4: 0.01982988 | AB4: 0.152019 | AC4: 0.233585

Sheet Stock returns
A1: ticker | B1: first_date | C1: close | D1: 1M | E1: 3M | F1: YTD | G1: 1Y | H1: 3Y | I1: 5Y | J1: 5Y_vol | K1: 5Y_max_drawdown
A2: MTRN | B2: 1980-03-17 | C2: 251.53 | D2: -0.046779441 | E2: -0.084737769 | F2: 1.0276204 | G2: 1.0665648 | H2: 1.4228029 | I2: 2.6221877 | J2: 0.45564237 | K2: -0.47844143
A3: SPY | B3: 1993-01-29 | C3: 761.69 | D3: -0.0050408383 | E3: 0.022553314 | F3: 0.12570291 | G3: 0.16576898 | H3: 0.78032474 | I3: 0.84498932 | J3: 0.17195166 | K3: -0.24496406
A4: IWM | B4: 2000-05-26 | C4: 284.10001 | D4: -0.051254088 | E4: -0.036361173 | F4: 0.16195676 | G4: 0.17213881 | H4: 0.61794986 | I4: 0.36251806 | J4: 0.22411414 | K4: -0.31911651
A5: XLB | B5: 1998-12-22 | C5: 49.990002 | D5: -0.034569277 | E5: -0.031520601 | F5: 0.11135753 | G5: 0.12029576 | H5: 0.30162507 | I5: 0.35732146 | J5: 0.19114016 | K5: -0.24716337
A6: ENTG | B6: 2000-07-11 | C6: 142.25 | D6: -0.053370627 | E6: -0.20361088 | F6: 0.69243155 | G6: 0.48737094 | H6: 0.55023057 | I6: 0.098193437 | J6: 0.55190773 | K6: -0.59319559
A7: CRS | B7: 1973-02-21 | C7: 408.12 | D7: -0.23247772 | E7: -0.30381576 | F7: 0.29817188 | G7: 0.65783759 | H7: 5.1315988 | I7: 12.69372 | J7: 0.4657014 | K7: -0.41858335
A8: ATI | B8: 1999-11-29 | C8: 191.63 | D8: -0.153802 | E8: -0.048226838 | F8: 0.66983271 | G8: 1.3810884 | H8: 3.3701257 | I8: 10.433771 | J8: 0.42914323 | K8: -0.38015062
A9: VNP.TO | B9: 2007-12-20 | C9: 26.389999 | D9: -0.099931799 | E9: -0.35743853 | F9: 0.48927768 | G9: 0.7091969 | H9: 6.6051871 | I9: 7.8557044 | J9: 0.54308177 | K9: -0.65273309

Sheet Events
A1: date | B1: event | C1: evidence | D1: return_1d | E1: excess_spy_1d | F1: return_3d | G1: excess_spy_3d | H1: return_5d | I1: excess_spy_5d | J1: next_day
A2: 2007-02-12 | B2: Large historical move; specific catalyst unverified | C2: unverified | D2: 0.33322694 | E2: 0.33663093 | F2: 0.44037002 | G2: 0.4287683 | H2: 0.45153058 | I2: 0.43909456 | J2: 0.049270757
A3: 2020-03-16 | B3: Pandemic market selloff; macro association | C3: context | D3: -0.15865889 | E3: -0.049235174 | F3: -0.29329461 | G3: -0.18442789 | H3: -0.18690604 | I3: -0.041448721 | J3: 0.042987187
A4: 2022-11-02 | B4: Q3 2022 earnings | C4: company earnings | D4: -0.21513393 | E4: -0.19003783 | F4: -0.16076826 | G4: -0.13952091 | H4: -0.11222346 | I4: -0.10566981 | J4: 0.035152902
A5: 2023-02-16 | B5: FY2022 earnings and 2023 outlook | C5: company earnings | D5: 0.24122751 | E5: 0.25499627 | F5: 0.21381013 | G5: 0.24977825 | H5: 0.22369406 | I5: 0.25586978 | J5: 0.017543867
A6: 2024-02-15 | B6: FY2023 earnings and 2024 outlook | C6: company earnings | D6: 0.10489533 | E6: 0.097995537 | F6: 0.056828217 | G6: 0.060458495 | H6: 0.064069541 | I6: 0.046158237 | J6: 0.0015276409
A7: 2025-07-30 | B7: Q2 2025 earnings; China and tariff uncertainty | C7: company earnings | D7: 0.10373679 | E7: 0.10499607 | F7: 0.14132087 | G7: 0.1626351 | H7: 0.17923108 | I7: 0.19070681 | J7: 0.036315461
A8: 2025-10-29 | B8: Q3 2025 earnings date listed on IR calendar | C8: company event | D8: -0.13272093 | E8: -0.13320133 | F8: -0.14384946 | G8: -0.13657213 | H8: -0.16722677 | I8: -0.15002302 | J8: -0.0052531107
A9: 2026-02-12 | B9: FY2025 earnings; $65m defense customer investment | C9: company earnings | D9: 0.012029803 | E9: 0.027478711 | F9: -0.024186818 | G9: -0.01102127 | H9: -0.038965851 | I9: -0.028155847 | J9: 0.0042765999
A10: 2026-04-29 | B10: Q1 2026 results; improved outlook | C10: company earnings | D10: -0.026737347 | E10: -0.026582713 | F10: 0.06171038 | G10: 0.049120692 | H10: 0.11078521 | I10: 0.093811543 | J10: 0.065318194
A11: 2026-07-28 | B11: Large decline; specific catalyst unverified | C11: unverified | D11: -0.13282609 | E11: -0.13522086 | F11: -0.13940119 | G11: -0.14291896 | H11: -0.1161608 | I11: -0.14129976 | J11: -0.097091084
A12: 2026-07-29 | B12: Second consecutive large decline; catalyst unverified | C12: unverified | D12: -0.097091084 | E12: -0.081703639 | F12: 0.0054363476 | G12: -0.0028919045 | H12: 0.082975743 | I12: 0.041847855 | J12: 0.099133886
A13: 2026-07-30 | B13: Rebound; company-specific catalyst unverified | C13: unverified | D13: 0.099133886 | E13: 0.082368142 | F13: 0.1288159 | G13: 0.09014352 | H13: 0.56902922 | I13: 0.51374183 | J13: 0.013118026
A14: 2026-08-05 | B14: Record Q2 2026; raised outlook | C14: company earnings | D14: 0.30814608 | E14: 0.31014264 | F14: 0.27719053 | G14: 0.27468834 | H14: 0.23645968 | I14: 0.23745792 | J14: -0.063349827
A15: 2026-09-16 | B15: FOMC raises rates 25bp; coincidence does not establish causality | C15: macro event | D15: 0.036871563 | E15: 0.041281444 | F15: 0.050317368 | G15: 0.042142685 | H15: Data unavailable | I15: Data unavailable | J15: 0.0086988187

Sheet Options snapshot
A1: contract | B1: expiration | C1: type | D1: strike | E1: spot | F1: bid | G1: ask | H1: last | I1: volume | J1: open_interest | K1: iv | L1: vendor_delta | M1: vendor_gamma | N1: vendor_theta | O1: vendor_vega | P1: quote_timestamp | Q1: last_trade_timestamp | R1: underlying_last_trade_timestamp | S1: multiplier | T1: midpoint | U1: spread_pct | V1: days_to_expiration | W1: moneyness | X1: same_session | Y1: trade_age_days | Z1: usable | AA1: liquidity_screen
A2: MTRN261016C00230000 | B2: 2026-10-16 | C2: call | D2: 230 | E2: 251.53 | F2: 25.7 | G2: 29 | H2: 0 | I2: 0 | J2: 0 | K2: 0.4956 | L2: 0.7632 | M2: 0.0084 | N2: -0.201 | O2: 0.2158 | P2: 2026-09-19 01:47:18 | Q2: Data unavailable | R2: 2026-09-18T15:59:59 | S2: 100 | T2: 27.35 | U2: 0.12065814 | V2: 28 | W2: 1.0936087 | X2: 1 | Y2: Data unavailable | Z2: 0 | AA2: 0
A3: MTRN261016P00230000 | B3: 2026-10-16 | C3: put | D3: 230 | E3: 251.53 | F3: 3 | G3: 7.3 | H3: 0 | I3: 0 | J3: 0 | K3: 0.5084 | L3: -0.2382 | M3: 0.0085 | N3: -0.2023 | O3: 0.2165 | P3: 2026-09-19 01:47:18 | Q3: Data unavailable | R3: 2026-09-18T15:59:59 | S3: 100 | T3: 5.15 | U3: 0.83495146 | V3: 28 | W3: 1.0936087 | X3: 1 | Y3: Data unavailable | Z3: 0 | AA3: 0
A4: MTRN261016C00240000 | B4: 2026-10-16 | C4: call | D4: 240 | E4: 251.53 | F4: 19.5 | G4: 22.9 | H4: 27.51 | I4: 0 | J4: 2 | K4: 0.5185 | L4: 0.6657 | M4: 0.0101 | N4: -0.2346 | O4: 0.2542 | P4: 2026-09-19 01:47:18 | Q4: 2026-09-09T10:01:39 | R4: 2026-09-18T15:59:59 | S4: 100 | T4: 21.2 | U4: 0.16037736 | V4: 28 | W4: 1.0480417 | X4: 1 | Y4: 9 | Z4: 0 | AA4: 0
A5: MTRN261016P00240000 | B5: 2026-10-16 | C5: put | D5: 240 | E5: 251.53 | F5: 6.4 | G5: 10.5 | H5: 0 | I5: 0 | J5: 0 | K5: 0.508 | L5: -0.3364 | M5: 0.0102 | N5: -0.2364 | O5: 0.2545 | P5: 2026-09-19 01:47:18 | Q5: Data unavailable | R5: 2026-09-18T15:59:59 | S5: 100 | T5: 8.45 | U5: 0.4852071 | V5: 28 | W5: 1.0480417 | X5: 1 | Y5: Data unavailable | Z5: 0 | AA5: 0
A6: MTRN261016C00250000 | B6: 2026-10-16 | C6: call | D6: 250 | E6: 251.53 | F6: 13.5 | G6: 17.5 | H6: 0 | I6: 0 | J6: 0 | K6: 0.5126 | L6: 0.5572 | M6: 0.011 | N6: -0.2542 | O6: 0.2755 | P6: 2026-09-19 01:47:18 | Q6: Data unavailable | R6: 2026-09-18T15:59:59 | S6: 100 | T6: 15.5 | U6: 0.25806452 | V6: 28 | W6: 1.00612 | X6: 1 | Y6: Data unavailable | Z6: 0 | AA6: 0
A7: MTRN261016P00250000 | B7: 2026-10-16 | C7: put | D7: 250 | E7: 251.53 | F7: 11.2 | G7: 15 | H7: 0 | I7: 0 | J7: 0 | K7: 0.5158 | L7: -0.4458 | M7: 0.0111 | N7: -0.2565 | O7: 0.2755 | P7: 2026-09-19 01:47:18 | Q7: Data unavailable | R7: 2026-09-18T15:59:59 | S7: 100 | T7: 13.1 | U7: 0.29007634 | V7: 28 | W7: 1.00612 | X7: 1 | Y7: Data unavailable | Z7: 0 | AA7: 0
A8: MTRN261016C00260000 | B8: 2026-10-16 | C8: call | D8: 260 | E8: 251.53 | F8: 9.4 | G8: 13 | H8: 16.65 | I8: 0 | J8: 2 | K8: 0.5176 | L8: 0.4492 | M8: 0.0109 | N8: -0.2566 | O8: 0.276 | P8: 2026-09-19 01:47:18 | Q8: 2026-09-08T11:51:36 | R8: 2026-09-18T15:59:59 | S8: 100 | T8: 11.2 | U8: 0.32142857 | V8: 28 | W8: 0.96742308 | X8: 1 | Y8: 10 | Z8: 0 | AA8: 0
A9: MTRN261016P00260000 | B9: 2026-10-16 | C9: put | D9: 260 | E9: 251.53 | F9: 17.2 | G9: 20.5 | H9: 39.56 | I9: 0 | J9: 1 | K9: 0.5226 | L9: -0.5549 | M9: 0.011 | N9: -0.2595 | O9: 0.2753 | P9: 2026-09-19 01:47:18 | Q9: 2026-08-24T09:59:09 | R9: 2026-09-18T15:59:59 | S9: 100 | T9: 18.85 | U9: 0.17506631 | V9: 28 | W9: 0.96742308 | X9: 1 | Y9: 25 | Z9: 0 | AA9: 0
A10: MTRN261016C00270000 | B10: 2026-10-16 | C10: call | D10: 270 | E10: 251.53 | F10: 6.5 | G10: 9.8 | H10: 7.9 | I10: 1 | J10: 1 | K10: 0.5318 | L10: 0.3517 | M10: 0.0101 | N10: -0.2438 | O10: 0.259 | P10: 2026-09-19 01:47:18 | Q10: 2026-09-18T09:44:57 | R10: 2026-09-18T15:59:59 | S10: 100 | T10: 8.15 | U10: 0.40490798 | V10: 28 | W10: 0.93159259 | X10: 1 | Y10: 0 | Z10: 0 | AA10: 0
A11: MTRN261016P00270000 | B11: 2026-10-16 | C11: put | D11: 270 | E11: 251.53 | F11: 24.2 | G11: 27.5 | H11: 0 | I11: 0 | J11: 0 | K11: 0.5386 | L11: -0.6536 | M11: 0.0102 | N11: -0.2474 | O11: 0.2566 | P11: 2026-09-19 01:47:18 | Q11: Data unavailable | R11: 2026-09-18T15:59:59 | S11: 100 | T11: 25.85 | U11: 0.12765957 | V11: 28 | W11: 0.93159259 | X11: 1 | Y11: Data unavailable | Z11: 0 | AA11: 0
A12: MTRN261016C00280000 | B12: 2026-10-16 | C12: call | D12: 280 | E12: 251.53 | F12: 3.8 | G12: 7.5 | H12: 5.5 | I12: 3 | J12: 1 | K12: 0.5351 | L12: 0.27 | M12: 0.0088 | N12: -0.2211 | O12: 0.231 | P12: 2026-09-19 01:47:18 | Q12: 2026-09-18T11:03:12 | R12: 2026-09-18T15:59:59 | S12: 100 | T12: 5.65 | U12: 0.65486726 | V12: 28 | W12: 0.89832143 | X12: 1 | Y12: 0 | Z12: 0 | AA12: 0
A13: MTRN261016P00280000 | B13: 2026-10-16 | C13: put | D13: 280 | E13: 251.53 | F13: 31.9 | G13: 35 | H13: 0 | I13: 0 | J13: 0 | K13: 0.546 | L13: -0.7365 | M13: 0.009 | N13: -0.2253 | O13: 0.2276 | P13: 2026-09-19 01:47:18 | Q13: Data unavailable | R13: 2026-09-18T15:59:59 | S13: 100 | T13: 33.45 | U13: 0.092675635 | V13: 28 | W13: 0.89832143 | X13: 1 | Y13: Data unavailable | Z13: 0 | AA13: 0
A14: MTRN261120C00230000 | B14: 2026-11-20 | C14: call | D14: 230 | E14: 251.53 | F14: 34 | G14: 37.7 | H14: 0 | I14: 0 | J14: 0 | K14: 0.5602 | L14: 0.7035 | M14: 0.0059 | N14: -0.1612 | O14: 0.3621 | P14: 2026-09-19 01:47:18 | Q14: Data unavailable | R14: 2026-09-18T15:59:59 | S14: 100 | T14: 35.85 | U14: 0.10320781 | V14: 63 | W14: 1.0936087 | X14: 1 | Y14: Data unavailable | Z14: 0 | AA14: 0
A15: MTRN261120P00230000 | B15: 2026-11-20 | C15: put | D15: 230 | E15: 251.53 | F15: 10.5 | G15: 14.4 | H15: 0 | I15: 0 | J15: 0 | K15: 0.5582 | L15: -0.2986 | M15: 0.0059 | N15: -0.1627 | O15: 0.3629 | P15: 2026-09-19 01:47:18 | Q15: Data unavailable | R15: 2026-09-18T15:59:59 | S15: 100 | T15: 12.45 | U15: 0.31325301 | V15: 63 | W15: 1.0936087 | X15: 1 | Y15: Data unavailable | Z15: 0 | AA15: 0
A16: MTRN261120C00240000 | B16: 2026-11-20 | C16: call | D16: 240 | E16: 251.53 | F16: 28.2 | G16: 32.4 | H16: 0 | I16: 0 | J16: 0 | K16: 0.5662 | L16: 0.6378 | M16: 0.0063 | N16: -0.1756 | O16: 0.3923 | P16: 2026-09-19 01:47:18 | Q16: Data unavailable | R16: 2026-09-18T15:59:59 | S16: 100 | T16: 30.3 | U16: 0.13861386 | V16: 63 | W16: 1.0480417 | X16: 1 | Y16: Data unavailable | Z16: 0 | AA16: 0
A17: MTRN261120P00240000 | B17: 2026-11-20 | C17: put | D17: 240 | E17: 251.53 | F17: 14.9 | G17: 19 | H17: 0 | I17: 0 | J17: 0 | K17: 0.5669 | L17: -0.3649 | M17: 0.0064 | N17: -0.1775 | O17: 0.393 | P17: 2026-09-19 01:47:18 | Q17: Data unavailable | R17: 2026-09-18T15:59:59 | S17: 100 | T17: 16.95 | U17: 0.24188791 | V17: 63 | W17: 1.0480417 | X17: 1 | Y17: Data unavailable | Z17: 0 | AA17: 0
A18: MTRN261120C00250000 | B18: 2026-11-20 | C18: call | D18: 250 | E18: 251.53 | F18: 23.5 | G18: 27.5 | H18: 0 | I18: 0 | J18: 0 | K18: 0.5729 | L18: 0.5713 | M18: 0.0066 | N18: -0.185 | O18: 0.4107 | P18: 2026-09-19 01:47:18 | Q18: Data unavailable | R18: 2026-09-18T15:59:59 | S18: 100 | T18: 25.5 | U18: 0.15686275 | V18: 63 | W18: 1.00612 | X18: 1 | Y18: Data unavailable | Z18: 0 | AA18: 0
A19: MTRN261120P00250000 | B19: 2026-11-20 | C19: put | D19: 250 | E19: 251.53 | F19: 20 | G19: 24.2 | H19: 0 | I19: 0 | J19: 0 | K19: 0.5734 | L19: -0.4322 | M19: 0.0067 | N19: -0.1875 | O19: 0.4108 | P19: 2026-09-19 01:47:18 | Q19: Data unavailable | R19: 2026-09-18T15:59:59 | S19: 100 | T19: 22.1 | U19: 0.19004525 | V19: 63 | W19: 1.00612 | X19: 1 | Y19: Data unavailable | Z19: 0 | AA19: 0
A20: MTRN261120C00260000 | B20: 2026-11-20 | C20: call | D20: 260 | E20: 251.53 | F20: 19.2 | G20: 23.3 | H20: 0 | I20: 0 | J20: 0 | K20: 0.5765 | L20: 0.5065 | M20: 0.0066 | N20: -0.1895 | O20: 0.4173 | P20: 2026-09-19 01:47:18 | Q20: Data unavailable | R20: 2026-09-18T15:59:59 | S20: 100 | T20: 21.25 | U20: 0.19294118 | V20: 63 | W20: 0.96742308 | X20: 1 | Y20: Data unavailable | Z20: 0 | AA20: 0
A21: MTRN261120P00260000 | B21: 2026-11-20 | C21: put | D21: 260 | E21: 251.53 | F21: 25.7 | G21: 29.5 | H21: 0 | I21: 0 | J21: 0 | K21: 0.5718 | L21: -0.498 | M21: 0.0068 | N21: -0.1925 | O21: 0.4165 | P21: 2026-09-19 01:47:18 | Q21: Data unavailable | R21: 2026-09-18T15:59:59 | S21: 100 | T21: 27.6 | U21: 0.13768116 | V21: 63 | W21: 0.96742308 | X21: 1 | Y21: Data unavailable | Z21: 0 | AA21: 0
A22: MTRN261120C00270000 | B22: 2026-11-20 | C22: call | D22: 270 | E22: 251.53 | F22: 15.8 | G22: 19.5 | H22: 0 | I22: 0 | J22: 0 | K22: 0.5808 | L22: 0.4452 | M22: 0.0065 | N22: -0.1894 | O22: 0.4133 | P22: 2026-09-19 01:47:18 | Q22: Data unavailable | R22: 2026-09-18T15:59:59 | S22: 100 | T22: 17.65 | U22: 0.20963173 | V22: 63 | W22: 0.93159259 | X22: 1 | Y22: Data unavailable | Z22: 0 | AA22: 0
A23: MTRN261120P00270000 | B23: 2026-11-20 | C23: put | D23: 270 | E23: 251.53 | F23: 32.2 | G23: 36 | H23: 0 | I23: 0 | J23: 0 | K23: 0.5791 | L23: -0.5604 | M23: 0.0066 | N23: -0.1931 | O23: 0.4117 | P23: 2026-09-19 01:47:18 | Q23: Data unavailable | R23: 2026-09-18T15:59:59 | S23: 100 | T23: 34.1 | U23: 0.11143695 | V23: 63 | W23: 0.93159259 | X23: 1 | Y23: Data unavailable | Z23: 0 | AA23: 0
A24: MTRN261120C00280000 | B24: 2026-11-20 | C24: call | D24: 280 | E24: 251.53 | F24: 12.8 | G24: 16 | H24: 0 | I24: 0 | J24: 0 | K24: 0.58 | L24: 0.3886 | M24: 0.0063 | N24: -0.1855 | O24: 0.4009 | P24: 2026-09-19 01:47:18 | Q24: Data unavailable | R24: 2026-09-18T15:59:59 | S24: 100 | T24: 14.4 | U24: 0.22222222 | V24: 63 | W24: 0.89832143 | X24: 1 | Y24: Data unavailable | Z24: 0 | AA24: 0
A25: MTRN261120P00280000 | B25: 2026-11-20 | C25: put | D25: 280 | E25: 251.53 | F25: 39.5 | G25: 43 | H25: 0 | I25: 0 | J25: 0 | K25: 0.5886 | L25: -0.6182 | M25: 0.0064 | N25: -0.1898 | O25: 0.3979 | P25: 2026-09-19 01:47:18 | Q25: Data unavailable | R25: 2026-09-18T15:59:59 | S25: 100 | T25: 41.25 | U25: 0.084848485 | V25: 63 | W25: 0.89832143 | X25: 1 | Y25: Data unavailable | Z25: 0 | AA25: 0
A26: MTRN261218C00230000 | B26: 2026-12-18 | C26: call | D26: 230 | E26: 251.53 | F26: 38.5 | G26: 42 | H26: 39 | I26: 0 | J26: 38 | K26: 0.5616 | L26: 0.6922 | M26: 0.005 | N26: -0.1354 | O26: 0.4424 | P26: 2026-09-19 01:47:18 | Q26: 2026-09-08T09:34:51 | R26: 2026-09-18T15:59:59 | S26: 100 | T26: 40.25 | U26: 0.086956522 | V26: 91 | W26: 1.0936087 | X26: 1 | Y26: 10 | Z26: 0 | AA26: 1
A27: MTRN261218P00230000 | B27: 2026-12-18 | C27: put | D27: 230 | E27: 251.53 | F27: 14.4 | G27: 18.5 | H27: 16.9 | I27: 0 | J27: 2 | K27: 0.5614 | L27: -0.3109 | M27: 0.0051 | N27: -0.1374 | O27: 0.4441 | P27: 2026-09-19 01:47:18 | Q27: 2026-08-18T13:06:35 | R27: 2026-09-18T15:59:59 | S27: 100 | T27: 16.45 | U27: 0.24924012 | V27: 91 | W27: 1.0936087 | X27: 1 | Y27: 31 | Z27: 0 | AA27: 0
A28: MTRN261218C00240000 | B28: 2026-12-18 | C28: call | D28: 240 | E28: 251.53 | F28: 33.2 | G28: 36.5 | H28: 32.6 | I28: 0 | J28: 25 | K28: 0.5638 | L28: 0.6368 | M28: 0.0053 | N28: -0.1448 | O28: 0.4718 | P28: 2026-09-19 01:47:18 | Q28: 2026-09-10T10:18:06 | R28: 2026-09-18T15:59:59 | S28: 100 | T28: 34.85 | U28: 0.094691535 | V28: 91 | W28: 1.0480417 | X28: 1 | Y28: 8 | Z28: 0 | AA28: 1
A29: MTRN261218P00240000 | B29: 2026-12-18 | C29: put | D29: 240 | E29: 251.53 | F29: 19.3 | G29: 23 | H29: 34.86 | I29: 0 | J29: 1 | K29: 0.5672 | L29: -0.3671 | M29: 0.0054 | N29: -0.1471 | O29: 0.4727 | P29: 2026-09-19 01:47:18 | Q29: 2026-06-11T13:10:47 | R29: 2026-09-18T15:59:59 | S29: 100 | T29: 21.15 | U29: 0.1749409 | V29: 91 | W29: 1.0480417 | X29: 1 | Y29: 99 | Z29: 0 | AA29: 0
A30: MTRN261218C00250000 | B30: 2026-12-18 | C30: call | D30: 250 | E30: 251.53 | F30: 28.2 | G30: 32 | H30: 25.5 | I30: 0 | J30: 17 | K30: 0.5621 | L30: 0.581 | M30: 0.0055 | N30: -0.1511 | O30: 0.4911 | P30: 2026-09-19 01:47:18 | Q30: 2026-08-26T12:53:22 | R30: 2026-09-18T15:59:59 | S30: 100 | T30: 30.1 | U30: 0.12624585 | V30: 91 | W30: 1.00612 | X30: 1 | Y30: 23 | Z30: 0 | AA30: 0
A31: MTRN261218P00250000 | B31: 2026-12-18 | C31: put | D31: 250 | E31: 251.53 | F31: 24.3 | G31: 28 | H31: 26.6 | I31: 0 | J31: 10 | K31: 0.5666 | L31: -0.4239 | M31: 0.0056 | N31: -0.1539 | O31: 0.4913 | P31: 2026-09-19 01:47:18 | Q31: 2026-09-14T09:30:02 | R31: 2026-09-18T15:59:59 | S31: 100 | T31: 26.15 | U31: 0.1414914 | V31: 91 | W31: 1.00612 | X31: 1 | Y31: 4 | Z31: 0 | AA31: 0
A32: MTRN261218C00260000 | B32: 2026-12-18 | C32: call | D32: 260 | E32: 251.53 | F32: 23.5 | G32: 27.5 | H32: 30.2 | I32: 0 | J32: 11 | K32: 0.5573 | L32: 0.5262 | M32: 0.0056 | N32: -0.1544 | O32: 0.5003 | P32: 2026-09-19 01:47:18 | Q32: 2026-09-08T11:21:50 | R32: 2026-09-18T15:59:59 | S32: 100 | T32: 25.5 | U32: 0.15686275 | V32: 91 | W32: 0.96742308 | X32: 1 | Y32: 10 | Z32: 0 | AA32: 0
A33: MTRN261218P00260000 | B33: 2026-12-18 | C33: put | D33: 260 | E33: 251.53 | F33: 29.6 | G33: 33.5 | H33: 25 | I33: 0 | J33: 1 | K33: 0.5628 | L33: -0.4798 | M33: 0.0058 | N33: -0.1577 | O33: 0.4996 | P33: 2026-09-19 01:47:18 | Q33: 2026-08-11T10:28:17 | R33: 2026-09-18T15:59:59 | S33: 100 | T33: 31.55 | U33: 0.12361331 | V33: 91 | W33: 0.96742308 | X33: 1 | Y33: 38 | Z33: 0 | AA33: 0
A34: MTRN261218C00270000 | B34: 2026-12-18 | C34: call | D34: 270 | E34: 251.53 | F34: 19.7 | G34: 23.5 | H34: 17 | I34: 0 | J34: 3 | K34: 0.5611 | L34: 0.4733 | M34: 0.0056 | N34: -0.1549 | O34: 0.5002 | P34: 2026-09-19 01:47:18 | Q34: 2026-08-21T13:04:14 | R34: 2026-09-18T15:59:59 | S34: 100 | T34: 21.6 | U34: 0.17592593 | V34: 91 | W34: 0.93159259 | X34: 1 | Y34: 28 | Z34: 0 | AA34: 0
A35: MTRN261218P00270000 | B35: 2026-12-18 | C35: put | D35: 270 | E35: 251.53 | F35: 35.6 | G35: 39.5 | H35: 28.84 | I35: 0 | J35: 2 | K35: 0.5602 | L35: -0.5339 | M35: 0.0057 | N35: -0.1587 | O35: 0.498 | P35: 2026-09-19 01:47:18 | Q35: 2026-08-05T13:07:14 | R35: 2026-09-18T15:59:59 | S35: 100 | T35: 37.55 | U35: 0.10386152 | V35: 91 | W35: 0.93159259 | X35: 1 | Y35: 44 | Z35: 0 | AA35: 0
A36: MTRN261218C00280000 | B36: 2026-12-18 | C36: call | D36: 280 | E36: 251.53 | F36: 16.5 | G36: 20 | H36: 14.54 | I36: 0 | J36: 8 | K36: 0.5559 | L36: 0.4233 | M36: 0.0055 | N36: -0.1529 | O36: 0.4921 | P36: 2026-09-19 01:47:18 | Q36: 2026-09-03T10:14:53 | R36: 2026-09-18T15:59:59 | S36: 100 | T36: 18.25 | U36: 0.19178082 | V36: 91 | W36: 0.89832143 | X36: 1 | Y36: 15 | Z36: 0 | AA36: 0
A37: MTRN261218P00280000 | B37: 2026-12-18 | C37: put | D37: 280 | E37: 251.53 | F37: 42.4 | G37: 46.5 | H37: 35 | I37: 0 | J37: 52 | K37: 0.5659 | L37: -0.5853 | M37: 0.0056 | N37: -0.1572 | O37: 0.4877 | P37: 2026-09-19 01:47:18 | Q37: 2026-08-10T10:05:43 | R37: 2026-09-18T15:59:59 | S37: 100 | T37: 44.45 | U37: 0.09223847 | V37: 91 | W37: 0.89832143 | X37: 1 | Y37: 39 | Z37: 0 | AA37: 1
A38: MTRN270319C00230000 | B38: 2027-03-19 | C38: call | D38: 230 | E38: 251.53 | F38: 49.6 | G38: 54 | H38: 48 | I38: 0 | J38: 9 | K38: 0.5558 | L38: 0.6871 | M38: 0.0036 | N38: -0.0945 | O38: 0.6307 | P38: 2026-09-19 01:47:18 | Q38: 2026-09-04T10:50:25 | R38: 2026-09-18T15:59:59 | S38: 100 | T38: 51.8 | U38: 0.084942085 | V38: 182 | W38: 1.0936087 | X38: 1 | Y38: 14 | Z38: 0 | AA38: 0
A39: MTRN270319P00230000 | B39: 2027-03-19 | C39: put | D39: 230 | E39: 251.53 | F39: 23.5 | G39: 27.8 | H39: 0 | I39: 0 | J39: 0 | K39: 0.5597 | L39: -0.3192 | M39: 0.0037 | N39: -0.0983 | O39: 0.6334 | P39: 2026-09-19 01:47:18 | Q39: Data unavailable | R39: 2026-09-18T15:59:59 | S39: 100 | T39: 25.65 | U39: 0.16764133 | V39: 182 | W39: 1.0936087 | X39: 1 | Y39: Data unavailable | Z39: 0 | AA39: 0
A40: MTRN270319C00240000 | B40: 2027-03-19 | C40: call | D40: 240 | E40: 251.53 | F40: 44.7 | G40: 49.2 | H40: 36.6 | I40: 0 | J40: 4 | K40: 0.5578 | L40: 0.6481 | M40: 0.0037 | N40: -0.0995 | O40: 0.6605 | P40: 2026-09-19 01:47:18 | Q40: 2026-09-03T10:42:43 | R40: 2026-09-18T15:59:59 | S40: 100 | T40: 46.95 | U40: 0.095846645 | V40: 182 | W40: 1.0480417 | X40: 1 | Y40: 15 | Z40: 0 | AA40: 0
A41: MTRN270319P00240000 | B41: 2027-03-19 | C41: put | D41: 240 | E41: 251.53 | F41: 28.8 | G41: 32.7 | H41: 0 | I41: 0 | J41: 0 | K41: 0.5637 | L41: -0.3596 | M41: 0.0039 | N41: -0.1035 | O41: 0.6628 | P41: 2026-09-19 01:47:18 | Q41: Data unavailable | R41: 2026-09-18T15:59:59 | S41: 100 | T41: 30.75 | U41: 0.12682927 | V41: 182 | W41: 1.0480417 | X41: 1 | Y41: Data unavailable | Z41: 0 | AA41: 0
A42: MTRN270319C00250000 | B42: 2027-03-19 | C42: call | D42: 250 | E42: 251.53 | F42: 40.4 | G42: 44.8 | H42: 40.2 | I42: 0 | J42: 12 | K42: 0.5608 | L42: 0.6092 | M42: 0.0039 | N42: -0.1034 | O42: 0.6828 | P42: 2026-09-19 01:47:18 | Q42: 2026-09-14T12:00:48 | R42: 2026-09-18T15:59:59 | S42: 100 | T42: 42.6 | U42: 0.10328638 | V42: 182 | W42: 1.00612 | X42: 1 | Y42: 4 | Z42: 0 | AA42: 0
A43: MTRN270319P00250000 | B43: 2027-03-19 | C43: put | D43: 250 | E43: 251.53 | F43: 34.3 | G43: 38.2 | H43: 0 | I43: 0 | J43: 0 | K43: 0.5672 | L43: -0.3997 | M43: 0.004 | N43: -0.1075 | O43: 0.6838 | P43: 2026-09-19 01:47:18 | Q43: Data unavailable | R43: 2026-09-18T15:59:59 | S43: 100 | T43: 36.25 | U43: 0.10758621 | V43: 182 | W43: 1.00612 | X43: 1 | Y43: Data unavailable | Z43: 0 | AA43: 0
A44: MTRN270319C00260000 | B44: 2027-03-19 | C44: call | D44: 260 | E44: 251.53 | F44: 36.4 | G44: 40.9 | H44: 43.35 | I44: 0 | J44: 0 | K44: 0.5625 | L44: 0.5711 | M44: 0.0039 | N44: -0.1062 | O44: 0.6981 | P44: 2026-09-19 01:47:18 | Q44: 2026-09-11T09:55:55 | R44: 2026-09-18T15:59:59 | S44: 100 | T44: 38.65 | U44: 0.1164295 | V44: 182 | W44: 0.96742308 | X44: 1 | Y44: 7 | Z44: 0 | AA44: 0
A45: MTRN270319P00260000 | B45: 2027-03-19 | C45: put | D45: 260 | E45: 251.53 | F45: 39.8 | G45: 44 | H45: 0 | I45: 0 | J45: 0 | K45: 0.5669 | L45: -0.4393 | M45: 0.0041 | N45: -0.1104 | O45: 0.6977 | P45: 2026-09-19 01:47:18 | Q45: Data unavailable | R45: 2026-09-18T15:59:59 | S45: 100 | T45: 41.9 | U45: 0.10023866 | V45: 182 | W45: 0.96742308 | X45: 1 | Y45: Data unavailable | Z45: 0 | AA45: 0
A46: MTRN270319C00270000 | B46: 2027-03-19 | C46: call | D46: 270 | E46: 251.53 | F46: 32.7 | G46: 36.9 | H46: 62.8 | I46: 0 | J46: 1 | K46: 0.5624 | L46: 0.534 | M46: 0.004 | N46: -0.108 | O46: 0.7066 | P46: 2026-09-19 01:47:18 | Q46: 2026-08-10T10:40:03 | R46: 2026-09-18T15:59:59 | S46: 100 | T46: 34.8 | U46: 0.12068966 | V46: 182 | W46: 0.93159259 | X46: 1 | Y46: 39 | Z46: 0 | AA46: 0
A47: MTRN270319P00270000 | B47: 2027-03-19 | C47: put | D47: 270 | E47: 251.53 | F47: 46 | G47: 50 | H47: 0 | I47: 0 | J47: 0 | K47: 0.5673 | L47: -0.4782 | M47: 0.0041 | N47: -0.1124 | O47: 0.7034 | P47: 2026-09-19 01:47:18 | Q47: Data unavailable | R47: 2026-09-18T15:59:59 | S47: 100 | T47: 48 | U47: 0.083333333 | V47: 182 | W47: 0.93159259 | X47: 1 | Y47: Data unavailable | Z47: 0 | AA47: 0
A48: MTRN270319C00280000 | B48: 2027-03-19 | C48: call | D48: 280 | E48: 251.53 | F48: 29 | G48: 33.5 | H48: 55.15 | I48: 0 | J48: 1 | K48: 0.5646 | L48: 0.4983 | M48: 0.004 | N48: -0.1089 | O48: 0.709 | P48: 2026-09-19 01:47:18 | Q48: 2026-08-05T10:52:17 | R48: 2026-09-18T15:59:59 | S48: 100 | T48: 31.25 | U48: 0.144 | V48: 182 | W48: 0.89832143 | X48: 1 | Y48: 44 | Z48: 0 | AA48: 0
A49: MTRN270319P00280000 | B49: 2027-03-19 | C49: put | D49: 280 | E49: 251.53 | F49: 52.5 | G49: 56.5 | H49: 46.1 | I49: 0 | J49: 3 | K49: 0.5689 | L49: -0.5154 | M49: 0.0042 | N49: -0.1134 | O49: 0.7043 | P49: 2026-09-19 01:47:18 | Q49: 2026-08-06T10:24:12 | R49: 2026-09-18T15:59:59 | S49: 100 | T49: 54.5 | U49: 0.073394495 | V49: 182 | W49: 0.89832143 | X49: 1 | Y49: 43 | Z49: 0 | AA49: 0

Sheet Options summary
A1: expiration | B1: contracts | C1: usable | D1: call_volume | E1: put_volume | F1: call_oi | G1: put_oi | H1: put_call_volume | I1: put_call_oi | J1: median_spread | K1: atm_strike | L1: atm_iv | M1: days
A2: 2026-09-18 | B2: 98 | C2: 0 | D2: 12 | E2: 2 | F2: 965 | G2: 120 | H2: 0.16666667 | I2: 0.12435233 | J2: 1.8604651 | K2: 250 | L2: 1.2817 | M2: 0
A3: 2026-10-16 | B3: 42 | C3: 0 | D3: 8 | E3: 0 | F3: 32 | G3: 33 | H3: 0 | I3: 1.03125 | J3: 0.27407043 | K3: 250 | L3: 0.5142 | M3: 28
A4: 2026-11-20 | B4: 34 | C4: 0 | D4: 0 | E4: 3 | F4: 0 | G4: 0 | H4: Data unavailable | I4: Data unavailable | J4: 0.173454 | K4: 250 | L4: 0.57315 | M4: 63
A5: 2026-12-18 | B5: 92 | C5: 0 | D5: 0 | E5: 3 | F5: 371 | G5: 197 | H5: Data unavailable | I5: 0.5309973 | J5: 0.13386862 | K5: 250 | L5: 0.56435 | M5: 91
A6: 2027-03-19 | B6: 86 | C6: 0 | D6: 0 | E6: 4 | F6: 86 | G6: 36 | H6: Data unavailable | I6: 0.41860465 | J6: 0.1054363 | K6: 250 | L6: 0.564 | M6: 182

Sheet Financial audit
A1: metric | B1: tag | C1: namespace | D1: unit | E1: start | F1: end | G1: val | H1: accn | I1: fy | J1: fp | K1: form | L1: filed | M1: frame
A2: revenue | B2: RevenueFromContractWithCustomerExcludingAssessedTax | C2: us-gaap | D2: USD | E2: 2021-01-01 | F2: 2021-12-31 | G2: 1510644000 | H2: 0001104657-24-000019 | I2: 2023 | J2: FY | K2: 10-K | L2: 2024-02-15 | M2: CY2021
A3: gross_profit | B3: GrossProfit | C3: us-gaap | D3: USD | E3: 2021-01-01 | F3: 2021-12-31 | G3: 283762000 | H3: 0001104657-24-000019 | I3: 2023 | J3: FY | K3: 10-K | L3: 2024-02-15 | M3: CY2021
A4: operating_income | B4: OperatingIncomeLoss | C4: us-gaap | D4: USD | E4: 2021-01-01 | F4: 2021-12-31 | G4: 77111000 | H4: 0001104657-24-000019 | I4: 2023 | J4: FY | K4: 10-K | L4: 2024-02-15 | M4: CY2021
A5: net_income | B5: NetIncomeLoss | C5: us-gaap | D5: USD | E5: 2021-01-01 | F5: 2021-12-31 | G5: 72474000 | H5: 0001104657-24-000019 | I5: 2023 | J5: FY | K5: 10-K | L5: 2024-02-15 | M5: CY2021
A6: tax | B6: IncomeTaxExpenseBenefit | C6: us-gaap | D6: USD | E6: 2021-01-01 | F6: 2021-12-31 | G6: 4851000 | H6: 0001104657-24-000019 | I6: 2023 | J6: FY | K6: 10-K | L6: 2024-02-15 | M6: CY2021
A7: interest | B7: MISSING | C7: Data unavailable | D7: USD | E7: 2021-01-01 | F7: 2021-12-31 | G7: Data unavailable | H7: Data unavailable | I7: Data unavailable | J7: Data unavailable | K7: Data unavailable | L7: Data unavailable | M7: Data unavailable
A8: cfo | B8: NetCashProvidedByUsedInOperatingActivities | C8: us-gaap | D8: USD | E8: 2021-01-01 | F8: 2021-12-31 | G8: 90241000 | H8: 0001104657-24-000019 | I8: 2023 | J8: FY | K8: 10-K | L8: 2024-02-15 | M8: CY2021
A9: ppe_capex | B9: PaymentsToAcquirePropertyPlantAndEquipment | C9: us-gaap | D9: USD | E9: 2021-01-01 | F9: 2021-12-31 | G9: 102910000 | H9: 0001104657-24-000019 | I9: 2023 | J9: FY | K9: 10-K | L9: 2024-02-15 | M9: CY2021
A10: mine_capex | B10: MISSING | C10: Data unavailable | D10: USD | E10: 2021-01-01 | F10: 2021-12-31 | G10: Data unavailable | H10: Data unavailable | I10: Data unavailable | J10: Data unavailable | K10: Data unavailable | L10: Data unavailable | M10: Data unavailable
A11: da | B11: DepreciationDepletionAndAmortization | C11: us-gaap | D11: USD | E11: 2021-01-01 | F11: 2021-12-31 | G11: 44137000 | H11: 0001104657-24-000019 | I11: 2023 | J11: FY | K11: 10-K | L11: 2024-02-15 | M11: CY2021
A12: amortization | B12: AmortizationOfIntangibleAssets | C12: us-gaap | D12: USD | E12: 2021-01-01 | F12: 2021-12-31 | G12: 5973000 | H12: 0001104657-24-000019 | I12: 2023 | J12: FY | K12: 10-K | L12: 2024-02-15 | M12: CY2021
A13: sbc | B13: ShareBasedCompensation | C13: us-gaap | D13: USD | E13: 2021-01-01 | F13: 2021-12-31 | G13: 6517000 | H13: 0001104657-24-000019 | I13: 2023 | J13: FY | K13: 10-K | L13: 2024-02-15 | M13: CY2021
A14: rnd | B14: ResearchAndDevelopmentExpense | C14: us-gaap | D14: USD | E14: 2021-01-01 | F14: 2021-12-31 | G14: 26575000 | H14: 0001104657-24-000019 | I14: 2023 | J14: FY | K14: 10-K | L14: 2024-02-15 | M14: CY2021
A15: dividends | B15: PaymentsOfDividendsCommonStock | C15: us-gaap | D15: USD | E15: 2021-01-01 | F15: 2021-12-31 | G15: 9697000 | H15: 0001104657-24-000019 | I15: 2023 | J15: FY | K15: 10-K | L15: 2024-02-15 | M15: CY2021
A16: repurchases | B16: PaymentsForRepurchaseOfCommonStock | C16: us-gaap | D16: USD | E16: 2021-01-01 | F16: 2021-12-31 | G16: 0 | H16: 0001104657-23-000019 | I16: 2022 | J16: FY | K16: 10-K | L16: 2023-02-16 | M16: CY2021
A17: diluted_shares | B17: WeightedAverageNumberOfDilutedSharesOutstanding | C17: us-gaap | D17: shares | E17: 2021-01-01 | F17: 2021-12-31 | G17: 20689000 | H17: 0001104657-24-000019 | I17: 2023 | J17: FY | K17: 10-K | L17: 2024-02-15 | M17: CY2021
A18: basic_shares | B18: WeightedAverageNumberOfSharesOutstandingBasic | C18: us-gaap | D18: shares | E18: 2021-01-01 | F18: 2021-12-31 | G18: 20422000 | H18: 0001104657-24-000019 | I18: 2023 | J18: FY | K18: 10-K | L18: 2024-02-15 | M18: CY2021
A19: eps | B19: EarningsPerShareDiluted | C19: us-gaap | D19: USD/shares | E19: 2021-01-01 | F19: 2021-12-31 | G19: 3.5 | H19: 0001104657-24-000019 | I19: 2023 | J19: FY | K19: 10-K | L19: 2024-02-15 | M19: CY2021
A20: cash | B20: CashAndCashEquivalentsAtCarryingValue | C20: us-gaap | D20: USD | E20: Data unavailable | F20: 2021-12-31 | G20: 14462000 | H20: 0001104657-23-000019 | I20: 2022 | J20: FY | K20: 10-K | L20: 2023-02-16 | M20: CY2021Q4I
A21: assets | B21: Assets | C21: us-gaap | D21: USD | E21: Data unavailable | F21: 2021-12-31 | G21: 1607479000 | H21: 0001104657-23-000019 | I21: 2022 | J21: FY | K21: 10-K | L21: 2023-02-16 | M21: CY2021Q4I
A22: current_assets | B22: AssetsCurrent | C22: us-gaap | D22: USD | E22: Data unavailable | F22: 2021-12-31 | G22: 627252000 | H22: 0001104657-23-000019 | I22: 2022 | J22: FY | K22: 10-K | L22: 2023-02-16 | M22: CY2021Q4I
A23: liabilities | B23: MISSING | C23: Data unavailable | D23: USD | E23: Data unavailable | F23: 2021-12-31 | G23: Data unavailable | H23: Data unavailable | I23: Data unavailable | J23: Data unavailable | K23: Data unavailable | L23: Data unavailable | M23: Data unavailable
A24: current_liabilities | B24: LiabilitiesCurrent | C24: us-gaap | D24: USD | E24: Data unavailable | F24: 2021-12-31 | G24: 204509000 | H24: 0001104657-23-000019 | I24: 2022 | J24: FY | K24: 10-K | L24: 2023-02-16 | M24: CY2021Q4I
A25: equity | B25: StockholdersEquity | C25: us-gaap | D25: USD | E25: Data unavailable | F25: 2021-12-31 | G25: 720440000 | H25: 0001104657-25-000024 | I25: 2024 | J25: FY | K25: 10-K | L25: 2025-02-19 | M25: CY2021Q4I
A26: debt_current | B26: LongTermDebtCurrent | C26: us-gaap | D26: USD | E26: Data unavailable | F26: 2021-12-31 | G26: 15359000 | H26: 0001104657-23-000019 | I26: 2022 | J26: FY | K26: 10-K | L26: 2023-02-16 | M26: CY2021Q4I
A27: debt_noncurrent | B27: LongTermDebtNoncurrent | C27: us-gaap | D27: USD | E27: Data unavailable | F27: 2021-12-31 | G27: 434388000 | H27: 0001104657-23-000019 | I27: 2022 | J27: FY | K27: 10-K | L27: 2023-02-16 | M27: CY2021Q4I
A28: debt_face | B28: LongTermDebt | C28: us-gaap | D28: USD | E28: Data unavailable | F28: 2021-12-31 | G28: 454548000 | H28: 0001104657-23-000019 | I28: 2022 | J28: FY | K28: 10-K | L28: 2023-02-16 | M28: CY2021Q4I
A29: goodwill | B29: Goodwill | C29: us-gaap | D29: USD | E29: Data unavailable | F29: 2021-12-31 | G29: 318620000 | H29: 0001104657-24-000019 | I29: 2023 | J29: FY | K29: 10-K | L29: 2024-02-15 | M29: CY2021Q4I
A30: intangibles | B30: FiniteLivedIntangibleAssetsNet | C30: us-gaap | D30: USD | E30: Data unavailable | F30: 2021-12-31 | G30: 156736000 | H30: 0001104657-23-000019 | I30: 2022 | J30: FY | K30: 10-K | L30: 2023-02-16 | M30: CY2021Q4I
A31: receivables | B31: AccountsReceivableNetCurrent | C31: us-gaap | D31: USD | E31: Data unavailable | F31: 2021-12-31 | G31: 213819000 | H31: 0001104657-23-000019 | I31: 2022 | J31: FY | K31: 10-K | L31: 2023-02-16 | M31: CY2021Q4I
A32: inventory | B32: InventoryNet | C32: us-gaap | D32: USD | E32: Data unavailable | F32: 2021-12-31 | G32: 361115000 | H32: 0001104657-23-000019 | I32: 2022 | J32: FY | K32: 10-K | L32: 2023-02-16 | M32: CY2021Q4I
A33: payables | B33: AccountsPayableCurrent | C33: us-gaap | D33: USD | E33: Data unavailable | F33: 2021-12-31 | G33: 86243000 | H33: 0001104657-23-000019 | I33: 2022 | J33: FY | K33: 10-K | L33: 2023-02-16 | M33: CY2021Q4I
A34: shares_issued | B34: CommonStockSharesIssued | C34: us-gaap | D34: shares | E34: Data unavailable | F34: 2021-12-31 | G34: 27148000 | H34: 0001104657-23-000019 | I34: 2022 | J34: FY | K34: 10-K | L34: 2023-02-16 | M34: CY2021Q4I
A35: treasury_shares | B35: TreasuryStockShares | C35: us-gaap | D35: shares | E35: Data unavailable | F35: 2021-12-31 | G35: 6700000 | H35: 0001104657-23-000019 | I35: 2022 | J35: FY | K35: 10-K | L35: 2023-02-16 | M35: CY2021Q4I
... A46: ppe_capex | B46: PaymentsToAcquirePropertyPlantAndEquipment | C46: us-gaap | D46: USD | E46: 2022-01-01 | F46: 2022-12-31 | G46: 77608000 | H46: 0001104657-25-000024 | I46: 2024 | J46: FY | K46: 10-K | L46: 2025-02-19 | M46: CY2022
A47: mine_capex | B47: MISSING | C47: Data unavailable | D47: USD | E47: 2022-01-01 | F47: 2022-12-31 | G47: Data unavailable | H47: Data unavailable | I47: Data unavailable | J47: Data unavailable | K47: Data unavailable | L47: Data unavailable | M47: Data unavailable
A48: da | B48: DepreciationDepletionAndAmortization | C48: us-gaap | D48: USD | E48: 2022-01-01 | F48: 2022-12-31 | G48: 53436000 | H48: 0001104657-25-000024 | I48: 2024 | J48: FY | K48: 10-K | L48: 2025-02-19 | M48: CY2022
A49: amortization | B49: AmortizationOfIntangibleAssets | C49: us-gaap | D49: USD | E49: 2022-01-01 | F49: 2022-12-31 | G49: 12400000 | H49: 0001104657-25-000024 | I49: 2024 | J49: FY | K49: 10-K | L49: 2025-02-19 | M49: CY2022
A50: sbc | B50: ShareBasedCompensation | C50: us-gaap | D50: USD | E50: 2022-01-01 | F50: 2022-12-31 | G50: 8813000 | H50: 0001104657-25-000024 | I50: 2024 | J50: FY | K50: 10-K | L50: 2025-02-19 | M50: CY2022
A51: rnd | B51: ResearchAndDevelopmentExpense | C51: us-gaap | D51: USD | E51: 2022-01-01 | F51: 2022-12-31 | G51: 28977000 | H51: 0001104657-25-000024 | I51: 2024 | J51: FY | K51: 10-K | L51: 2025-02-19 | M51: CY2022
A52: dividends | B52: PaymentsOfDividendsCommonStock | C52: us-gaap | D52: USD | E52: 2022-01-01 | F52: 2022-12-31 | G52: 10160000 | H52: 0001104657-25-000024 | I52: 2024 | J52: FY | K52: 10-K | L52: 2025-02-19 | M52: CY2022
A53: repurchases | B53: PaymentsForRepurchaseOfCommonStock | C53: us-gaap | D53: USD | E53: 2022-01-01 | F53: 2022-12-31 | G53: 0 | H53: 0001104657-23-000019 | I53: 2022 | J53: FY | K53: 10-K | L53: 2023-02-16 | M53: CY2022
A54: diluted_shares | B54: WeightedAverageNumberOfDilutedSharesOutstanding | C54: us-gaap | D54: shares | E54: 2022-01-01 | F54: 2022-12-31 | G54: 20760000 | H54: 0001104657-25-000024 | I54: 2024 | J54: FY | K54: 10-K | L54: 2025-02-19 | M54: CY2022
A55: basic_shares | B55: WeightedAverageNumberOfSharesOutstandingBasic | C55: us-gaap | D55: shares | E55: 2022-01-01 | F55: 2022-12-31 | G55: 20511000 | H55: 0001104657-25-000024 | I55: 2024 | J55: FY | K55: 10-K | L55: 2025-02-19 | M55: CY2022
A56: eps | B56: EarningsPerShareDiluted | C56: us-gaap | D56: USD/shares | E56: 2022-01-01 | F56: 2022-12-31 | G56: 4.14 | H56: 0001104657-25-000024 | I56: 2024 | J56: FY | K56: 10-K | L56: 2025-02-19 | M56: CY2022
A57: cash | B57: CashAndCashEquivalentsAtCarryingValue | C57: us-gaap | D57: USD | E57: Data unavailable | F57: 2022-12-31 | G57: 13101000 | H57: 0001104657-24-000019 | I57: 2023 | J57: FY | K57: 10-K | L57: 2024-02-15 | M57: CY2022Q4I
A58: assets | B58: Assets | C58: us-gaap | D58: USD | E58: Data unavailable | F58: 2022-12-31 | G58: 1691979000 | H58: 0001104657-24-000019 | I58: 2023 | J58: FY | K58: 10-K | L58: 2024-02-15 | M58: CY2022Q4I
A59: current_assets | B59: AssetsCurrent | C59: us-gaap | D59: USD | E59: Data unavailable | F59: 2022-12-31 | G59: 690448000 | H59: 0001104657-24-000019 | I59: 2023 | J59: FY | K59: 10-K | L59: 2024-02-15 | M59: CY2022Q4I
A60: liabilities | B60: MISSING | C60: Data unavailable | D60: USD | E60: Data unavailable | F60: 2022-12-31 | G60: Data unavailable | H60: Data unavailable | I60: Data unavailable | J60: Data unavailable | K60: Data unavailable | L60: Data unavailable | M60: Data unavailable
A61: current_liabilities | B61: LiabilitiesCurrent | C61: us-gaap | D61: USD | E61: Data unavailable | F61: 2022-12-31 | G61: 238964000 | H61: 0001104657-24-000019 | I61: 2023 | J61: FY | K61: 10-K | L61: 2024-02-15 | M61: CY2022Q4I
A62: equity | B62: StockholdersEquity | C62: us-gaap | D62: USD | E62: Data unavailable | F62: 2022-12-31 | G62: 799990000 | H62: 0001104657-26-000011 | I62: 2025 | J62: FY | K62: 10-K | L62: 2026-02-12 | M62: CY2022Q4I
A63: debt_current | B63: LongTermDebtCurrent | C63: us-gaap | D63: USD | E63: Data unavailable | F63: 2022-12-31 | G63: 21105000 | H63: 0001104657-24-000019 | I63: 2023 | J63: FY | K63: 10-K | L63: 2024-02-15 | M63: CY2022Q4I
A64: debt_noncurrent | B64: LongTermDebtNoncurrent | C64: us-gaap | D64: USD | E64: Data unavailable | F64: 2022-12-31 | G64: 410876000 | H64: 0001104657-24-000019 | I64: 2023 | J64: FY | K64: 10-K | L64: 2024-02-15 | M64: CY2022Q4I
A65: debt_face | B65: LongTermDebt | C65: us-gaap | D65: USD | E65: Data unavailable | F65: 2022-12-31 | G65: 435791000 | H65: 0001104657-24-000019 | I65: 2023 | J65: FY | K65: 10-K | L65: 2024-02-15 | M65: CY2022Q4I
A66: goodwill | B66: Goodwill | C66: us-gaap | D66: USD | E66: Data unavailable | F66: 2022-12-31 | G66: 319498000 | H66: 0001104657-25-000024 | I66: 2024 | J66: FY | K66: 10-K | L66: 2025-02-19 | M66: CY2022Q4I
A67: intangibles | B67: FiniteLivedIntangibleAssetsNet | C67: us-gaap | D67: USD | E67: Data unavailable | F67: 2022-12-31 | G67: 139601000 | H67: 0001104657-24-000019 | I67: 2023 | J67: FY | K67: 10-K | L67: 2024-02-15 | M67: CY2022Q4I
A68: receivables | B68: AccountsReceivableNetCurrent | C68: us-gaap | D68: USD | E68: Data unavailable | F68: 2022-12-31 | G68: 215211000 | H68: 0001104657-24-000019 | I68: 2023 | J68: FY | K68: 10-K | L68: 2024-02-15 | M68: CY2022Q4I
A69: inventory | B69: InventoryNet | C69: us-gaap | D69: USD | E69: Data unavailable | F69: 2022-12-31 | G69: 423080000 | H69: 0001104657-24-000019 | I69: 2023 | J69: FY | K69: 10-K | L69: 2024-02-15 | M69: CY2022Q4I
A70: payables | B70: AccountsPayableCurrent | C70: us-gaap | D70: USD | E70: Data unavailable | F70: 2022-12-31 | G70: 107899000 | H70: 0001104657-24-000019 | I70: 2023 | J70: FY | K70: 10-K | L70: 2024-02-15 | M70: CY2022Q4I
A71: shares_issued | B71: CommonStockSharesIssued | C71: us-gaap | D71: shares | E71: Data unavailable | F71: 2022-12-31 | G71: 27148000 | H71: 0001104657-24-000019 | I71: 2023 | J71: FY | K71: 10-K | L71: 2024-02-15 | M71: CY2022Q4I
A72: treasury_shares | B72: TreasuryStockCommonShares | C72: us-gaap | D72: shares | E72: Data unavailable | F72: 2022-12-31 | G72: 6605000 | H72: 0001104657-24-000019 | I72: 2023 | J72: FY | K72: 10-K | L72: 2024-02-15 | M72: CY2022Q4I
... A82: ppe_capex | B82: PaymentsToAcquireOtherPropertyPlantAndEquipment | C82: us-gaap | D82: USD | E82: 2023-01-01 | F82: 2023-12-31 | G82: 110550000 | H82: 0001104657-26-000011 | I82: 2025 | J82: FY | K82: 10-K | L82: 2026-02-12 | M82: CY2023
A83: mine_capex | B83: MISSING | C83: Data unavailable | D83: USD | E83: 2023-01-01 | F83: 2023-12-31 | G83: Data unavailable | H83: Data unavailable | I83: Data unavailable | J83: Data unavailable | K83: Data unavailable | L83: Data unavailable | M83: Data unavailable
A84: da | B84: DepreciationDepletionAndAmortization | C84: us-gaap | D84: USD | E84: 2023-01-01 | F84: 2023-12-31 | G84: 61644000 | H84: 0001104657-26-000011 | I84: 2025 | J84: FY | K84: 10-K | L84: 2026-02-12 | M84: CY2023
A85: amortization | B85: AmortizationOfIntangibleAssets | C85: us-gaap | D85: USD | E85: 2023-01-01 | F85: 2023-12-31 | G85: 12876000 | H85: 0001104657-26-000011 | I85: 2025 | J85: FY | K85: 10-K | L85: 2026-02-12 | M85: CY2023
A86: sbc | B86: ShareBasedCompensation | C86: us-gaap | D86: USD | E86: 2023-01-01 | F86: 2023-12-31 | G86: 10092000 | H86: 0001104657-26-000011 | I86: 2025 | J86: FY | K86: 10-K | L86: 2026-02-12 | M86: CY2023
A87: rnd | B87: ResearchAndDevelopmentExpense | C87: us-gaap | D87: USD | E87: 2023-01-01 | F87: 2023-12-31 | G87: 27540000 | H87: 0001104657-26-000011 | I87: 2025 | J87: FY | K87: 10-K | L87: 2026-02-12 | M87: CY2023
A88: dividends | B88: PaymentsOfDividendsCommonStock | C88: us-gaap | D88: USD | E88: 2023-01-01 | F88: 2023-12-31 | G88: 10621000 | H88: 0001104657-26-000011 | I88: 2025 | J88: FY | K88: 10-K | L88: 2026-02-12 | M88: CY2023
A89: repurchases | B89: PaymentsForRepurchaseOfCommonStock | C89: us-gaap | D89: USD | E89: 2023-01-01 | F89: 2023-12-31 | G89: 0 | H89: 0001104657-26-000011 | I89: 2025 | J89: FY | K89: 10-K | L89: 2026-02-12 | M89: CY2023
A90: diluted_shares | B90: WeightedAverageNumberOfDilutedSharesOutstanding | C90: us-gaap | D90: shares | E90: 2023-01-01 | F90: 2023-12-31 | G90: 20911000 | H90: 0001104657-26-000011 | I90: 2025 | J90: FY | K90: 10-K | L90: 2026-02-12 | M90: CY2023
A91: basic_shares | B91: WeightedAverageNumberOfSharesOutstandingBasic | C91: us-gaap | D91: shares | E91: 2023-01-01 | F91: 2023-12-31 | G91: 20619000 | H91: 0001104657-26-000011 | I91: 2025 | J91: FY | K91: 10-K | L91: 2026-02-12 | M91: CY2023
A92: eps | B92: EarningsPerShareDiluted | C92: us-gaap | D92: USD/shares | E92: 2023-01-01 | F92: 2023-12-31 | G92: 4.58 | H92: 0001104657-26-000011 | I92: 2025 | J92: FY | K92: 10-K | L92: 2026-02-12 | M92: CY2023
A93: cash | B93: CashAndCashEquivalentsAtCarryingValue | C93: us-gaap | D93: USD | E93: Data unavailable | F93: 2023-12-31 | G93: 13294000 | H93: 0001104657-25-000024 | I93: 2024 | J93: FY | K93: 10-K | L93: 2025-02-19 | M93: CY2023Q4I
A94: assets | B94: Assets | C94: us-gaap | D94: USD | E94: Data unavailable | F94: 2023-12-31 | G94: 1762726000 | H94: 0001104657-25-000024 | I94: 2024 | J94: FY | K94: 10-K | L94: 2025-02-19 | M94: CY2023Q4I
A95: current_assets | B95: AssetsCurrent | C95: us-gaap | D95: USD | E95: Data unavailable | F95: 2023-12-31 | G95: 709382000 | H95: 0001104657-25-000024 | I95: 2024 | J95: FY | K95: 10-K | L95: 2025-02-19 | M95: CY2023Q4I
A96: liabilities | B96: MISSING | C96: Data unavailable | D96: USD | E96: Data unavailable | F96: 2023-12-31 | G96: Data unavailable | H96: Data unavailable | I96: Data unavailable | J96: Data unavailable | K96: Data unavailable | L96: Data unavailable | M96: Data unavailable
A97: current_liabilities | B97: LiabilitiesCurrent | C97: us-gaap | D97: USD | E97: Data unavailable | F97: 2023-12-31 | G97: 254995000 | H97: 0001104657-25-000024 | I97: 2024 | J97: FY | K97: 10-K | L97: 2025-02-19 | M97: CY2023Q4I
A98: equity | B98: StockholdersEquity | C98: us-gaap | D98: USD | E98: Data unavailable | F98: 2023-12-31 | G98: 885053000 | H98: 0001104657-26-000011 | I98: 2025 | J98: FY | K98: 10-K | L98: 2026-02-12 | M98: CY2023Q4I
A99: debt_current | B99: LongTermDebtCurrent | C99: us-gaap | D99: USD | E99: Data unavailable | F99: 2023-12-31 | G99: 38597000 | H99: 0001104657-25-000024 | I99: 2024 | J99: FY | K99: 10-K | L99: 2025-02-19 | M99: CY2023Q4I
A100: debt_noncurrent | B100: LongTermDebtNoncurrent | C100: us-gaap | D100: USD | E100: Data unavailable | F100: 2023-12-31 | G100: 387576000 | H100: 0001104657-25-000024 | I100: 2024 | J100: FY | K100: 10-K | L100: 2025-02-19 | M100: CY2023Q4I
A101: debt_face | B101: LongTermDebt | C101: us-gaap | D101: USD | E101: Data unavailable | F101: 2023-12-31 | G101: 428993000 | H101: 0001104657-25-000024 | I101: 2024 | J101: FY | K101: 10-K | L101: 2025-02-19 | M101: CY2023Q4I
A102: goodwill | B102: Goodwill | C102: us-gaap | D102: USD | E102: Data unavailable | F102: 2023-12-31 | G102: 320873000 | H102: 0001104657-26-000011 | I102: 2025 | J102: FY | K102: 10-K | L102: 2026-02-12 | M102: CY2023Q4I
A103: intangibles | B103: IntangibleAssetsNetExcludingGoodwill | C103: us-gaap | D103: USD | E103: Data unavailable | F103: 2023-12-31 | G103: 133571000 | H103: 0001104657-25-000024 | I103: 2024 | J103: FY | K103: 10-K | L103: 2025-02-19 | M103: CY2023Q4I
A104: receivables | B104: AccountsReceivableNetCurrent | C104: us-gaap | D104: USD | E104: Data unavailable | F104: 2023-12-31 | G104: 192747000 | H104: 0001104657-25-000024 | I104: 2024 | J104: FY | K104: 10-K | L104: 2025-02-19 | M104: CY2023Q4I
A105: inventory | B105: InventoryNet | C105: us-gaap | D105: USD | E105: Data unavailable | F105: 2023-12-31 | G105: 441597000 | H105: 0001104657-25-000024 | I105: 2024 | J105: FY | K105: 10-K | L105: 2025-02-19 | M105: CY2023Q4I
A106: payables | B106: AccountsPayableCurrent | C106: us-gaap | D106: USD | E106: Data unavailable | F106: 2023-12-31 | G106: 125663000 | H106: 0001104657-25-000024 | I106: 2024 | J106: FY | K106: 10-K | L106: 2025-02-19 | M106: CY2023Q4I
A107: shares_issued | B107: CommonStockSharesIssued | C107: us-gaap | D107: shares | E107: Data unavailable | F107: 2023-12-31 | G107: 27148000 | H107: 0001104657-25-000024 | I107: 2024 | J107: FY | K107: 10-K | L107: 2025-02-19 | M107: CY2023Q4I
A108: treasury_shares | B108: TreasuryStockCommonShares | C108: us-gaap | D108: shares | E108: Data unavailable | F108: 2023-12-31 | G108: 6502000 | H108: 0001104657-25-000024 | I108: 2024 | J108: FY | K108: 10-K | L108: 2025-02-19 | M108: CY2023Q4I
... A118: ppe_capex | B118: PaymentsToAcquireOtherPropertyPlantAndEquipment | C118: us-gaap | D118: USD | E118: 2024-01-01 | F118: 2024-12-31 | G118: 68649000 | H118: 0001104657-26-000011 | I118: 2025 | J118: FY | K118: 10-K | L118: 2026-02-12 | M118: CY2024
A119: mine_capex | B119: MISSING | C119: Data unavailable | D119: USD | E119: 2024-01-01 | F119: 2024-12-31 | G119: Data unavailable | H119: Data unavailable | I119: Data unavailable | J119: Data unavailable | K119: Data unavailable | L119: Data unavailable | M119: Data unavailable
A120: da | B120: DepreciationDepletionAndAmortization | C120: us-gaap | D120: USD | E120: 2024-01-01 | F120: 2024-12-31 | G120: 68676000 | H120: 0001104657-26-000011 | I120: 2025 | J120: FY | K120: 10-K | L120: 2026-02-12 | M120: CY2024
A121: amortization | B121: AmortizationOfIntangibleAssets | C121: us-gaap | D121: USD | E121: 2024-01-01 | F121: 2024-12-31 | G121: 12134000 | H121: 0001104657-26-000011 | I121: 2025 | J121: FY | K121: 10-K | L121: 2026-02-12 | M121: CY2024
A122: sbc | B122: ShareBasedCompensation | C122: us-gaap | D122: USD | E122: 2024-01-01 | F122: 2024-12-31 | G122: 10560000 | H122: 0001104657-26-000011 | I122: 2025 | J122: FY | K122: 10-K | L122: 2026-02-12 | M122: CY2024
A123: rnd | B123: ResearchAndDevelopmentExpense | C123: us-gaap | D123: USD | E123: 2024-01-01 | F123: 2024-12-31 | G123: 29028000 | H123: 0001104657-26-000011 | I123: 2025 | J123: FY | K123: 10-K | L123: 2026-02-12 | M123: CY2024
A124: dividends | B124: PaymentsOfDividendsCommonStock | C124: us-gaap | D124: USD | E124: 2024-01-01 | F124: 2024-12-31 | G124: 11087000 | H124: 0001104657-26-000011 | I124: 2025 | J124: FY | K124: 10-K | L124: 2026-02-12 | M124: CY2024
A125: repurchases | B125: PaymentsForRepurchaseOfCommonStock | C125: us-gaap | D125: USD | E125: 2024-01-01 | F125: 2024-12-31 | G125: 0 | H125: 0001104657-26-000011 | I125: 2025 | J125: FY | K125: 10-K | L125: 2026-02-12 | M125: CY2024
A126: diluted_shares | B126: WeightedAverageNumberOfDilutedSharesOutstanding | C126: us-gaap | D126: shares | E126: 2024-01-01 | F126: 2024-12-31 | G126: 20928000 | H126: 0001104657-26-000011 | I126: 2025 | J126: FY | K126: 10-K | L126: 2026-02-12 | M126: CY2024
A127: basic_shares | B127: WeightedAverageNumberOfSharesOutstandingBasic | C127: us-gaap | D127: shares | E127: 2024-01-01 | F127: 2024-12-31 | G127: 20732000 | H127: 0001104657-26-000011 | I127: 2025 | J127: FY | K127: 10-K | L127: 2026-02-12 | M127: CY2024
A128: eps | B128: EarningsPerShareDiluted | C128: us-gaap | D128: USD/shares | E128: 2024-01-01 | F128: 2024-12-31 | G128: 0.28 | H128: 0001104657-26-000011 | I128: 2025 | J128: FY | K128: 10-K | L128: 2026-02-12 | M128: CY2024
...

Sheet Manual input audit
A1: metric | B1: period | C1: value | D1: unit | E1: classification | F1: source_key | G1: source_url | H1: local_path | I1: locator
A2: value_added_sales | B2: 2021 | C2: 829.572 | D2: USD millions unless noted | E2: reported | F2: K23 | G2: https://www.sec.gov/Archives/edgar/data/1104657/000110465724000019/mtrn-20231231.htm | H2: report/company_filings/10-K_2024-02-15_mtrn-20231231.htm | I2: MD&A, net sales / pass-through reconciliation
A3: adjusted_ebitda | B3: 2021 | C3: 143.6 | D3: USD millions unless noted | E3: reported | F3: HISTDECK | G3: https://www.sec.gov/Archives/edgar/data/1104657/000110465723000047/materioncorporationinves.htm | H3: report/earnings_materials/Investor_2023.htm | I3: EBITDA reconciliation; TTM slide 16; historical 2023 investor deck slide 22
A4: value_added_sales | B4: 2022 | C4: 1114.411 | D4: USD millions unless noted | E4: reported | F4: K23 | G4: https://www.sec.gov/Archives/edgar/data/1104657/000110465724000019/mtrn-20231231.htm | H4: report/company_filings/10-K_2024-02-15_mtrn-20231231.htm | I4: MD&A, net sales / pass-through reconciliation
A5: adjusted_ebitda | B5: 2022 | C5: 196 | D5: USD millions unless noted | E5: reported | F5: HISTDECK | G5: https://www.sec.gov/Archives/edgar/data/1104657/000110465723000047/materioncorporationinves.htm | H5: report/earnings_materials/Investor_2023.htm | I5: EBITDA reconciliation; TTM slide 16; historical 2023 investor deck slide 22
A6: value_added_sales | B6: 2023 | C6: 1127.071 | D6: USD millions unless noted | E6: reported | F6: K23 | G6: https://www.sec.gov/Archives/edgar/data/1104657/000110465724000019/mtrn-20231231.htm | H6: report/company_filings/10-K_2024-02-15_mtrn-20231231.htm | I6: MD&A, net sales / pass-through reconciliation
A7: adjusted_ebitda | B7: 2023 | C7: 217.7 | D7: USD millions unless noted | E7: reported | F7: DECK23 | G7: https://s203.q4cdn.com/782025361/files/doc_presentations/2024/02/1/Materion-Corporation-Q4-2023-Earnings-Presentation.pdf | H7: report/earnings_materials/Q4_2023_presentation.pdf | I7: Adjusted EBITDA reconciliation
A8: value_added_sales | B8: 2024 | C8: 1097.577 | D8: USD millions unless noted | E8: reported | F8: K25 | G8: https://www.sec.gov/Archives/edgar/data/1104657/000110465726000011/mtrn-20251231.htm | H8: report/company_filings/10-K_2026-02-12_mtrn-20251231.htm | I8: MD&A, net sales / pass-through reconciliation
A9: adjusted_ebitda | B9: 2024 | C9: 221.2 | D9: USD millions unless noted | E9: reported | F9: E25 | G9: https://www.sec.gov/Archives/edgar/data/1104657/000110465726000006/q42025pressrelease.htm | H9: report/earnings_materials/FY2025_release.htm | I9: EBITDA reconciliation; TTM slide 16; historical 2023 investor deck slide 22
A10: value_added_sales | B10: 2025 | C10: 1046.194 | D10: USD millions unless noted | E10: reported | F10: K25 | G10: https://www.sec.gov/Archives/edgar/data/1104657/000110465726000011/mtrn-20251231.htm | H10: report/company_filings/10-K_2026-02-12_mtrn-20251231.htm | I10: MD&A, net sales / pass-through reconciliation
A11: adjusted_ebitda | B11: 2025 | C11: 217 | D11: USD millions unless noted | E11: reported | F11: E25 | G11: https://www.sec.gov/Archives/edgar/data/1104657/000110465726000006/q42025pressrelease.htm | H11: report/earnings_materials/FY2025_release.htm | I11: EBITDA reconciliation; TTM slide 16; historical 2023 investor deck slide 22
A12: value_added_sales | B12: H1 2025 | C12: 528.316 | D12: USD millions unless noted | E12: reported | F12: Q26 | G12: https://www.sec.gov/Archives/edgar/data/1104657/000110465726000044/mtrn-20260703.htm | H12: report/company_filings/10-Q_2026-08-05_mtrn-20260703.htm | I12: MD&A, net sales / pass-through reconciliation
A13: adjusted_ebitda | B13: H1 2025 | C13: 104.5 | D13: USD millions unless noted | E13: reported | F13: E26 | G13: https://www.sec.gov/Archives/edgar/data/1104657/000110465726000042/q22026pressrelease.htm | H13: report/earnings_materials/Q2_2026_release.htm | I13: EBITDA reconciliation; TTM slide 16; historical 2023 investor deck slide 22
... A29: FY2026_VA_growth_anchor_percent | B29: latest / forecast | C29: 15 | D29: USD millions unless noted | E29: analyst interpretation | F29: E26 | G29: https://www.sec.gov/Archives/edgar/data/1104657/000110465726000042/q22026pressrelease.htm | H29: report/earnings_materials/Q2_2026_release.htm | I29: Mid-teens guidance interpreted as 15%

Sheet Peer financial audit
A1: ticker | B1: metric | C1: tag | D1: namespace | E1: unit | F1: start | G1: end | H1: val | I1: accn | J1: fy | K1: fp | L1: form | M1: filed | N1: frame
A2: ENTG | B2: RevenueFromContractWithCustomerExcludingAssessedTax | C2: RevenueFromContractWithCustomerExcludingAssessedTax | D2: us-gaap | E2: USD | F2: 2025-01-01 | G2: 2025-12-31 | H2: 3196600000 | I2: 0001101302-26-000012 | J2: 2025 | K2: FY | L2: 10-K | M2: 2026-02-11 | N2: CY2025
A3: ENTG | B3: RevenueFromContractWithCustomerExcludingAssessedTax | C3: RevenueFromContractWithCustomerExcludingAssessedTax | D3: us-gaap | E3: USD | F3: 2026-01-01 | G3: 2026-06-27 | H3: 1695100000 | I3: 0001101302-26-000150 | J3: 2026 | K3: Q2 | L3: 10-Q | M3: 2026-08-04 | N3: Data unavailable
A4: ENTG | B4: RevenueFromContractWithCustomerExcludingAssessedTax | C4: RevenueFromContractWithCustomerExcludingAssessedTax | D4: us-gaap | E4: USD | F4: 2025-01-01 | G4: 2025-06-28 | H4: 1565600000 | I4: 0001101302-26-000150 | J4: 2026 | K4: Q2 | L4: 10-Q | M4: 2026-08-04 | N4: Data unavailable
A5: ENTG | B5: NetIncomeLoss | C5: NetIncomeLoss | D5: us-gaap | E5: USD | F5: 2025-01-01 | G5: 2025-12-31 | H5: 235600000 | I5: 0001101302-26-000012 | J5: 2025 | K5: FY | L5: 10-K | M5: 2026-02-11 | N5: CY2025
A6: ENTG | B6: NetIncomeLoss | C6: NetIncomeLoss | D6: us-gaap | E6: USD | F6: 2026-01-01 | G6: 2026-06-27 | H6: 185600000 | I6: 0001101302-26-000150 | J6: 2026 | K6: Q2 | L6: 10-Q | M6: 2026-08-04 | N6: Data unavailable
A7: ENTG | B7: NetIncomeLoss | C7: NetIncomeLoss | D7: us-gaap | E7: USD | F7: 2025-01-01 | G7: 2025-06-28 | H7: 115700000 | I7: 0001101302-26-000150 | J7: 2026 | K7: Q2 | L7: 10-Q | M7: 2026-08-04 | N7: Data unavailable
A8: ENTG | B8: OperatingIncomeLoss | C8: OperatingIncomeLoss | D8: us-gaap | E8: USD | F8: 2025-01-01 | G8: 2025-12-31 | H8: 455900000 | I8: 0001101302-26-000012 | J8: 2025 | K8: FY | L8: 10-K | M8: 2026-02-11 | N8: CY2025
A9: ENTG | B9: OperatingIncomeLoss | C9: OperatingIncomeLoss | D9: us-gaap | E9: USD | F9: 2026-01-01 | G9: 2026-06-27 | H9: 306200000 | I9: 0001101302-26-000150 | J9: 2026 | K9: Q2 | L9: 10-Q | M9: 2026-08-04 | N9: Data unavailable
A10: ENTG | B10: OperatingIncomeLoss | C10: OperatingIncomeLoss | D10: us-gaap | E10: USD | F10: 2025-01-01 | G10: 2025-06-28 | H10: 228400000 | I10: 0001101302-26-000150 | J10: 2026 | K10: Q2 | L10: 10-Q | M10: 2026-08-04 | N10: Data unavailable
A11: ENTG | B11: GrossProfit | C11: GrossProfit | D11: us-gaap | E11: USD | F11: 2025-01-01 | G11: 2025-12-31 | H11: 1419900000 | I11: 0001101302-26-000012 | J11: 2025 | K11: FY | L11: 10-K | M11: 2026-02-11 | N11: CY2025
A12: ENTG | B12: GrossProfit | C12: GrossProfit | D12: us-gaap | E12: USD | F12: 2026-01-01 | G12: 2026-06-27 | H12: 800800000 | I12: 0001101302-26-000150 | J12: 2026 | K12: Q2 | L12: 10-Q | M12: 2026-08-04 | N12: Data unavailable
A13: ENTG | B13: GrossProfit | C13: GrossProfit | D13: us-gaap | E13: USD | F13: 2025-01-01 | G13: 2025-06-28 | H13: 708000000 | I13: 0001101302-26-000150 | J13: 2026 | K13: Q2 | L13: 10-Q | M13: 2026-08-04 | N13: Data unavailable
... A62: ATI | B62: WeightedAverageNumberOfDilutedSharesOutstanding | C62: WeightedAverageNumberOfDilutedSharesOutstanding | D62: us-gaap | E62: shares | F62: 2025-12-29 | G62: 2026-06-28 | H62: 138500000 | I62: 0001628280-26-054233 | J62: 2026 | K62: Q2 | L62: 10-Q | M62: 2026-08-06 | N62: Data unavailable

Sheet Sources
A1: id | B1: category | C1: source | D1: title | E1: publisher | F1: pub_date | G1: retrieved | H1: url | I1: local_path | J1: forecast_period | K1: key_data | L1: relevance | M1: source_type
A2: S001 | B2: financial_data | C2: SEC EDGAR | D2: MTRN SEC company facts | E2: SEC EDGAR | F2: Data unavailable | G2: 2026-09-19 | H2: https://data.sec.gov/api/xbrl/companyfacts/CIK0001104657.json | I2: data/financial_data/companyfacts_MTRN.json | J2: Data unavailable | K2: Data unavailable | L2: Data unavailable | M2: primary
A3: S002 | B3: financial_data | C3: SEC EDGAR | D3: ENTG SEC company facts | E3: SEC EDGAR | F3: Data unavailable | G3: 2026-09-19 | H3: https://data.sec.gov/api/xbrl/companyfacts/CIK0001101302.json | I3: data/financial_data/companyfacts_ENTG.json | J3: Data unavailable | K3: Data unavailable | L3: Data unavailable | M3: primary
A4: S003 | B4: financial_data | C4: SEC EDGAR | D4: CRS SEC company facts | E4: SEC EDGAR | F4: Data unavailable | G4: 2026-09-19 | H4: https://data.sec.gov/api/xbrl/companyfacts/CIK0000017843.json | I4: data/financial_data/companyfacts_CRS.json | J4: Data unavailable | K4: Data unavailable | L4: Data unavailable | M4: primary
A5: S004 | B5: financial_data | C5: SEC EDGAR | D5: ATI SEC company facts | E5: SEC EDGAR | F5: Data unavailable | G5: 2026-09-19 | H5: https://data.sec.gov/api/xbrl/companyfacts/CIK0001018963.json | I5: data/financial_data/companyfacts_ATI.json | J5: Data unavailable | K5: Data unavailable | L5: Data unavailable | M5: primary
A6: S005 | B6: company_filings | C6: SEC EDGAR / Materion | D6: MTRN 10-Q filed 2026-08-05; period 2026-07-03 | E6: SEC EDGAR / Materion | F6: 2026-08-05 | G6: 2026-09-19 | H6: https://www.sec.gov/Archives/edgar/data/1104657/000110465726000044/mtrn-20260703.htm | I6: report/company_filings/10-Q_2026-08-05_mtrn-20260703.htm | J6: Data unavailable | K6: Data unavailable | L6: Data unavailable | M6: primary
A7: S006 | B7: company_filings | C7: SEC EDGAR / Materion | D7: MTRN 8-K filed 2026-08-05; period 2026-08-05 | E7: SEC EDGAR / Materion | F7: 2026-08-05 | G7: 2026-09-19 | H7: https://www.sec.gov/Archives/edgar/data/1104657/000110465726000042/mtrn-20260805.htm | I7: report/company_filings/8-K_2026-08-05_mtrn-20260805.htm | J7: Data unavailable | K7: Data unavailable | L7: Data unavailable | M7: primary
A8: S007 | B8: company_filings | C8: SEC EDGAR / Materion | D8: MTRN 8-K filed 2026-05-07; period 2026-05-07 | E8: SEC EDGAR / Materion | F8: 2026-05-07 | G8: 2026-09-19 | H8: https://www.sec.gov/Archives/edgar/data/1104657/000110465726000031/mtrn-20260507.htm | I8: report/company_filings/8-K_2026-05-07_mtrn-20260507.htm | J8: Data unavailable | K8: Data unavailable | L8: Data unavailable | M8: primary
A9: S008 | B9: company_filings | C9: SEC EDGAR / Materion | D9: MTRN 10-Q filed 2026-04-29; period 2026-04-03 | E9: SEC EDGAR / Materion | F9: 2026-04-29 | G9: 2026-09-19 | H9: https://www.sec.gov/Archives/edgar/data/1104657/000110465726000029/mtrn-20260403.htm | I9: report/company_filings/10-Q_2026-04-29_mtrn-20260403.htm | J9: Data unavailable | K9: Data unavailable | L9: Data unavailable | M9: primary
A10: S009 | B10: company_filings | C10: SEC EDGAR / Materion | D10: MTRN 8-K filed 2026-04-29; period 2026-04-29 | E10: SEC EDGAR / Materion | F10: 2026-04-29 | G10: 2026-09-19 | H10: https://www.sec.gov/Archives/edgar/data/1104657/000110465726000026/mtrn-20260429.htm | I10: report/company_filings/8-K_2026-04-29_mtrn-20260429.htm | J10: Data unavailable | K10: Data unavailable | L10: Data unavailable | M10: primary
A11: S010 | B11: company_filings | C11: SEC EDGAR / Materion | D11: MTRN DEF 14A filed 2026-03-26; period 2026-05-07 | E11: SEC EDGAR / Materion | F11: 2026-03-26 | G11: 2026-09-19 | H11: https://www.sec.gov/Archives/edgar/data/1104657/000110465726000022/mtrn-20260326.htm | I11: report/company_filings/DEF14A_2026-03-26_mtrn-20260326.htm | J11: Data unavailable | K11: Data unavailable | L11: Data unavailable | M11: primary
A12: S011 | B12: company_filings | C12: SEC EDGAR / Materion | D12: MTRN 10-K filed 2026-02-12; period 2025-12-31 | E12: SEC EDGAR / Materion | F12: 2026-02-12 | G12: 2026-09-19 | H12: https://www.sec.gov/Archives/edgar/data/1104657/000110465726000011/mtrn-20251231.htm | I12: report/company_filings/10-K_2026-02-12_mtrn-20251231.htm | J12: Data unavailable | K12: Data unavailable | L12: Data unavailable | M12: primary
... A59: S058 | B59: other_evidence | C59: Materion | D59: Q3 2025 earnings event calendar | E59: Materion | F59: 2025-10-29 | G59: 2026-09-19 | H59: https://investor.materion.com/events-and-presentations/event-details/2025/Materion-Corporation-Third-Quarter-2025/default.aspx | I59: report/other_evidence/event_and_historical_research_web.txt | J59: Data unavailable | K59: Official-source web extract; see archived text | L59: Macro input or verified event date | M59: primary web extract
