Workbook

Sheet Inputs
A1: HPE valuation model — inputs
A2: Blue = input. Valuation date 11-Sep-2026. $ millions except per-share.
A4: Input | B4: Value | C4: Source / note
A5: Valuation date | B5: 46276 | C5: Last completed session before report date
A6: Share price ($) | B6: 62.09 | C6: Yahoo Finance close 11-Sep-2026
A7: Fully diluted shares (m) | B7: 1445.21 | C7: Dilution sheet
A8: Gross debt 31-Jul-2026 | B8: 20244 | C8: Q3 FY26 balance sheet (incl. Financial Services debt)
A9: Cash & equivalents 31-Jul-2026 | B9: 6216 | C9: Q3 FY26 balance sheet
A10: Non-controlling interests | B10: 62 | C10: Q3 FY26 balance sheet
A11: Risk-free rate (10Y UST) | B11: 0.0495 | C11: FRED DGS10, latest observation
A12: Equity risk premium | B12: 0.0397 | C12: Damodaran implied ERP, start-2026
A13: Unlevered beta — Computers/Peripherals | B13: 1.324587 | C13: Damodaran betas.xls Jan-2026 (cash-corrected)
A14: Unlevered beta — Telecom equipment | B14: 0.887251 | C14: Damodaran betas.xls Jan-2026 (cash-corrected)
A15: Networking weight (TTM segment profit) | B15: 0.4045 | C15: Segment analysis
A16: Default spread (BBB/Baa2) | B16: 0.011113 | C16: Damodaran synthetic rating table; S&P BBB
... A24: Terminal return on new capital | B24: 0.12 | C24: Analyst

Sheet WACC
A1: Cost of capital (live formulas)
A4: Item | B4: Value
A5: Unlevered beta (profit-weighted) | B5: =Inputs!$B$15*Inputs!$B$14+(1-Inputs!$B$15)*Inputs!$B$13
A6: Market value of equity (fully diluted) | B6: =Inputs!$B$6*Inputs!$B$7
A7: Debt / equity | B7: =Inputs!$B$8/B6
A8: Levered beta | B8: =B5*(1+(1-Inputs!$B$17)*B7)
A9: Cost of equity | B9: =Inputs!$B$11+B8*Inputs!$B$12
A10: Pre-tax cost of debt | B10: =Inputs!$B$11+Inputs!$B$16
A11: After-tax cost of debt | B11: =B10*(1-Inputs!$B$17)
A12: Equity weight | B12: =B6/(B6+Inputs!$B$8)
A13: WACC | B13: =B12*B9+(1-B12)*B11

Sheet DCF_Bear
A1: DCF — Bear case (live formulas)
A2: AI-server digestion and memory-cost normalisation reverse FY26 ASP gains; networking share loss to Cisco/Arista; margins revert toward the pre-Juniper mix-adjusted ~10–11%.
A4: Terminal growth | B4: 0.0225
A5: NWC investment (% of Δrevenue) | B5: 0.07
A6: Scenario probability | B6: 0.25
A8: $ millions | B8: FY2027E | C8: FY2028E | D8: FY2029E | E8: FY2030E | F8: FY2031E | G8: FY2032E | H8: FY2033E | I8: FY2034E | J8: FY2035E | K8: FY2036E
A9: Fiscal year end | B9: 2027 | C9: 2028 | D9: 2029 | E9: 2030 | F9: 2031 | G9: 2032 | H9: 2033 | I9: 2034 | J9: 2035 | K9: 2036
A10: Revenue growth | B10: 0.1 | C10: -0.03 | D10: 0.02 | E10: 0.025 | F10: 0.025 | G10: 0.025 | H10: 0.02 | I10: 0.02 | J10: 0.02 | K10: 0.02
A11: Non-GAAP operating margin | B11: 0.13 | C11: 0.11 | D11: 0.105 | E11: 0.105 | F11: 0.105 | G11: 0.105 | H11: 0.105 | I11: 0.105 | J11: 0.105 | K11: 0.105
A12: Revenue | B12: =Inputs!$B$19*(1+B10) | C12: =B12*(1+C10) | D12: =C12*(1+D10) | E12: =D12*(1+E10) | F12: =E12*(1+F10) | G12: =F12*(1+G10) | H12: =G12*(1+H10) | I12: =H12*(1+I10) | J12: =I12*(1+J10) | K12: =J12*(1+K10)
A13: SBC | B13: =B12*Inputs!$B$21 | C13: =C12*Inputs!$B$21 | D13: =D12*Inputs!$B$21 | E13: =E12*Inputs!$B$21 | F13: =F12*Inputs!$B$21 | G13: =G12*Inputs!$B$21 | H13: =H12*Inputs!$B$21 | I13: =I12*Inputs!$B$21 | ... K13: =K12*Inputs!$B$21
A14: Restructuring cash costs | B14: 300 | C14: 150 | D14: 0 | E14: 0 | F14: 0 | G14: 0 | H14: 0 | I14: 0 | J14: 0 | K14: 0
A15: EBIT (after SBC) | B15: =B12*(B11-Inputs!$B$21)-B14 | C15: =C12*(C11-Inputs!$B$21)-C14 | D15: =D12*(D11-Inputs!$B$21)-D14 | E15: =E12*(E11-Inputs!$B$21)-E14 | F15: =F12*(F11-Inputs!$B$21)-F14 | G15: =G12*(G11-Inputs!$B$21)-G14 | H15: =H12*(H11-Inputs!$B$21)-H14 | I15: =I12*(I11-Inputs!$B$21)-I14 | ... K15: =K12*(K11-Inputs!$B$21)-K14
A16: Operating taxes | B16: =B15*Inputs!$B$18 | C16: =C15*Inputs!$B$18 | D16: =D15*Inputs!$B$18 | E16: =E15*Inputs!$B$18 | F16: =F15*Inputs!$B$18 | G16: =G15*Inputs!$B$18 | H16: =H15*Inputs!$B$18 | I16: =I15*Inputs!$B$18 | ... K16: =K15*Inputs!$B$18
A17: NOPAT | B17: =B15-B16 | C17: =C15-C16 | D17: =D15-D16 | E17: =E15-E16 | F17: =F15-F16 | G17: =G15-G16 | H17: =H15-H16 | I17: =I15-I16 | ... K17: =K15-K16
A18: Depreciation | B18: =B12*Inputs!$B$22 | C18: =C12*Inputs!$B$22 | D18: =D12*Inputs!$B$22 | E18: =E12*Inputs!$B$22 | F18: =F12*Inputs!$B$22 | G18: =G12*Inputs!$B$22 | H18: =H12*Inputs!$B$22 | I18: =I12*Inputs!$B$22 | ... K18: =K12*Inputs!$B$22
A19: Net capex | B19: =B12*(Inputs!$B$22+Inputs!$B$23) | C19: =C12*(Inputs!$B$22+Inputs!$B$23) | D19: =D12*(Inputs!$B$22+Inputs!$B$23) | E19: =E12*(Inputs!$B$22+Inputs!$B$23) | F19: =F12*(Inputs!$B$22+Inputs!$B$23) | G19: =G12*(Inputs!$B$22+Inputs!$B$23) | H19: =H12*(Inputs!$B$22+Inputs!$B$23) | I19: =I12*(Inputs!$B$22+Inputs!$B$23) | ... K19: =K12*(Inputs!$B$22+Inputs!$B$23)
A20: Δ Net working capital | B20: =$B$5*(B12-Inputs!$B$19) | C20: =$B$5*(C12-B12) | D20: =$B$5*(D12-C12) | E20: =$B$5*(E12-D12) | F20: =$B$5*(F12-E12) | G20: =$B$5*(G12-F12) | H20: =$B$5*(H12-G12) | I20: =$B$5*(I12-H12) | J20: =$B$5*(J12-I12) | K20: =$B$5*(K12-J12)
A21: FCFF | B21: =B17+B18-B19-B20 | C21: =C17+C18-C19-C20 | D21: =D17+D18-D19-D20 | E21: =E17+E18-E19-E20 | F21: =F17+F18-F19-F20 | G21: =G17+G18-G19-G20 | H21: =H17+H18-H19-H20 | I21: =I17+I18-I19-I20 | ... K21: =K17+K18-K19-K20
A22: Years from valuation date (mid-year) | B22: =(DATE(B9,10,31)-182-Inputs!$B$5)/365.25 | C22: =(DATE(C9,10,31)-182-Inputs!$B$5)/365.25 | D22: =(DATE(D9,10,31)-182-Inputs!$B$5)/365.25 | E22: =(DATE(E9,10,31)-182-Inputs!$B$5)/365.25 | F22: =(DATE(F9,10,31)-182-Inputs!$B$5)/365.25 | G22: =(DATE(G9,10,31)-182-Inputs!$B$5)/365.25 | H22: =(DATE(H9,10,31)-182-Inputs!$B$5)/365.25 | I22: =(DATE(I9,10,31)-182-Inputs!$B$5)/365.25 | ... K22: =(DATE(K9,10,31)-182-Inputs!$B$5)/365.25
A23: Discount factor | B23: =1/(1+WACC!$B$13)^B22 | C23: =1/(1+WACC!$B$13)^C22 | D23: =1/(1+WACC!$B$13)^D22 | E23: =1/(1+WACC!$B$13)^E22 | F23: =1/(1+WACC!$B$13)^F22 | G23: =1/(1+WACC!$B$13)^G22 | H23: =1/(1+WACC!$B$13)^H22 | I23: =1/(1+WACC!$B$13)^I22 | ... K23: =1/(1+WACC!$B$13)^K22
A24: PV of FCFF | B24: =B21*B23 | C24: =C21*C23 | D24: =D21*D23 | E24: =E21*E23 | F24: =F21*F23 | G24: =G21*G23 | H24: =H21*H23 | I24: =I21*I23 | ... K24: =K21*K23
A26: PV of Q4 FY26E stub FCFF | B26: =Inputs!$B$20/(1+WACC!$B$13)^(30/365.25)
A27: PV of explicit FCFF FY27E–FY36E | B27: =SUM(B24:K24)
A28: Terminal-year NOPAT (FY37E) | B28: =K17*(1+B4)
A29: Terminal FCFF (after reinvestment at RONIC) | B29: =B28*(1-B4/Inputs!$B$24)
A30: Terminal value at FY36 end | B30: =B29/(WACC!$B$13-B4)
A31: PV of terminal value | B31: =B30/(1+WACC!$B$13)^((DATE(2036,10,31)-Inputs!$B$5)/365.25)
A32: Enterprise value | B32: =B26+B27+B31
A33: Less: gross debt | B33: =-Inputs!$B$8
A34: Plus: cash | B34: =Inputs!$B$9
A35: Less: non-controlling interests | B35: =-Inputs!$B$10
A36: Equity value | B36: =SUM(B32:B35)
A37: Fully diluted shares (m) | B37: =Inputs!$B$7
A38: Value per share ($) | B38: =B36/B37
A39: Terminal value share of EV | B39: =B31/B32
A40: Check: valuation.py value per share | B40: 22.191359

Sheet DCF_Base
A1: DCF — Base case (live formulas)
A2: FY27 in line with the raised framework (+13–17% revenue, 14–15% non-GAAP margin); growth fades to IDC/Gartner-consistent mid-single digits; margin settles at 12.5% as AI mix offsets networking mix.
A4: Terminal growth | B4: 0.0275
A5: NWC investment (% of Δrevenue) | B5: 0.06
A6: Scenario probability | B6: 0.5
A8: $ millions | B8: FY2027E | C8: FY2028E | D8: FY2029E | E8: FY2030E | F8: FY2031E | G8: FY2032E | H8: FY2033E | I8: FY2034E | J8: FY2035E | K8: FY2036E
A9: Fiscal year end | B9: 2027 | C9: 2028 | D9: 2029 | E9: 2030 | F9: 2031 | G9: 2032 | H9: 2033 | I9: 2034 | J9: 2035 | K9: 2036
A10: Revenue growth | B10: 0.15 | C10: 0.06 | D10: 0.05 | E10: 0.045 | F10: 0.04 | G10: 0.0375 | H10: 0.035 | I10: 0.0325 | J10: 0.03 | K10: 0.0275
A11: Non-GAAP operating margin | B11: 0.145 | C11: 0.135 | D11: 0.13 | E11: 0.125 | F11: 0.125 | G11: 0.125 | H11: 0.125 | I11: 0.125 | J11: 0.125 | K11: 0.125
A12: Revenue | B12: =Inputs!$B$19*(1+B10) | C12: =B12*(1+C10) | D12: =C12*(1+D10) | E12: =D12*(1+E10) | F12: =E12*(1+F10) | G12: =F12*(1+G10) | H12: =G12*(1+H10) | I12: =H12*(1+I10) | J12: =I12*(1+J10) | K12: =J12*(1+K10)
A13: SBC | B13: =B12*Inputs!$B$21 | C13: =C12*Inputs!$B$21 | D13: =D12*Inputs!$B$21 | E13: =E12*Inputs!$B$21 | F13: =F12*Inputs!$B$21 | G13: =G12*Inputs!$B$21 | H13: =H12*Inputs!$B$21 | I13: =I12*Inputs!$B$21 | ... K13: =K12*Inputs!$B$21
A14: Restructuring cash costs | B14: 300 | C14: 150 | D14: 0 | E14: 0 | F14: 0 | G14: 0 | H14: 0 | I14: 0 | J14: 0 | K14: 0
A15: EBIT (after SBC) | B15: =B12*(B11-Inputs!$B$21)-B14 | C15: =C12*(C11-Inputs!$B$21)-C14 | D15: =D12*(D11-Inputs!$B$21)-D14 | E15: =E12*(E11-Inputs!$B$21)-E14 | F15: =F12*(F11-Inputs!$B$21)-F14 | G15: =G12*(G11-Inputs!$B$21)-G14 | H15: =H12*(H11-Inputs!$B$21)-H14 | I15: =I12*(I11-Inputs!$B$21)-I14 | ... K15: =K12*(K11-Inputs!$B$21)-K14
A16: Operating taxes | B16: =B15*Inputs!$B$18 | C16: =C15*Inputs!$B$18 | D16: =D15*Inputs!$B$18 | E16: =E15*Inputs!$B$18 | F16: =F15*Inputs!$B$18 | G16: =G15*Inputs!$B$18 | H16: =H15*Inputs!$B$18 | I16: =I15*Inputs!$B$18 | ... K16: =K15*Inputs!$B$18
A17: NOPAT | B17: =B15-B16 | C17: =C15-C16 | D17: =D15-D16 | E17: =E15-E16 | F17: =F15-F16 | G17: =G15-G16 | H17: =H15-H16 | I17: =I15-I16 | ... K17: =K15-K16
A18: Depreciation | B18: =B12*Inputs!$B$22 | C18: =C12*Inputs!$B$22 | D18: =D12*Inputs!$B$22 | E18: =E12*Inputs!$B$22 | F18: =F12*Inputs!$B$22 | G18: =G12*Inputs!$B$22 | H18: =H12*Inputs!$B$22 | I18: =I12*Inputs!$B$22 | ... K18: =K12*Inputs!$B$22
A19: Net capex | B19: =B12*(Inputs!$B$22+Inputs!$B$23) | C19: =C12*(Inputs!$B$22+Inputs!$B$23) | D19: =D12*(Inputs!$B$22+Inputs!$B$23) | E19: =E12*(Inputs!$B$22+Inputs!$B$23) | F19: =F12*(Inputs!$B$22+Inputs!$B$23) | G19: =G12*(Inputs!$B$22+Inputs!$B$23) | H19: =H12*(Inputs!$B$22+Inputs!$B$23) | I19: =I12*(Inputs!$B$22+Inputs!$B$23) | ... K19: =K12*(Inputs!$B$22+Inputs!$B$23)
A20: Δ Net working capital | B20: =$B$5*(B12-Inputs!$B$19) | C20: =$B$5*(C12-B12) | D20: =$B$5*(D12-C12) | E20: =$B$5*(E12-D12) | F20: =$B$5*(F12-E12) | G20: =$B$5*(G12-F12) | H20: =$B$5*(H12-G12) | I20: =$B$5*(I12-H12) | J20: =$B$5*(J12-I12) | K20: =$B$5*(K12-J12)
A21: FCFF | B21: =B17+B18-B19-B20 | C21: =C17+C18-C19-C20 | D21: =D17+D18-D19-D20 | E21: =E17+E18-E19-E20 | F21: =F17+F18-F19-F20 | G21: =G17+G18-G19-G20 | H21: =H17+H18-H19-H20 | I21: =I17+I18-I19-I20 | ... K21: =K17+K18-K19-K20
A22: Years from valuation date (mid-year) | B22: =(DATE(B9,10,31)-182-Inputs!$B$5)/365.25 | C22: =(DATE(C9,10,31)-182-Inputs!$B$5)/365.25 | D22: =(DATE(D9,10,31)-182-Inputs!$B$5)/365.25 | E22: =(DATE(E9,10,31)-182-Inputs!$B$5)/365.25 | F22: =(DATE(F9,10,31)-182-Inputs!$B$5)/365.25 | G22: =(DATE(G9,10,31)-182-Inputs!$B$5)/365.25 | H22: =(DATE(H9,10,31)-182-Inputs!$B$5)/365.25 | I22: =(DATE(I9,10,31)-182-Inputs!$B$5)/365.25 | ... K22: =(DATE(K9,10,31)-182-Inputs!$B$5)/365.25
A23: Discount factor | B23: =1/(1+WACC!$B$13)^B22 | C23: =1/(1+WACC!$B$13)^C22 | D23: =1/(1+WACC!$B$13)^D22 | E23: =1/(1+WACC!$B$13)^E22 | F23: =1/(1+WACC!$B$13)^F22 | G23: =1/(1+WACC!$B$13)^G22 | H23: =1/(1+WACC!$B$13)^H22 | I23: =1/(1+WACC!$B$13)^I22 | ... K23: =1/(1+WACC!$B$13)^K22
A24: PV of FCFF | B24: =B21*B23 | C24: =C21*C23 | D24: =D21*D23 | E24: =E21*E23 | F24: =F21*F23 | G24: =G21*G23 | H24: =H21*H23 | I24: =I21*I23 | ... K24: =K21*K23
A26: PV of Q4 FY26E stub FCFF | B26: =Inputs!$B$20/(1+WACC!$B$13)^(30/365.25)
A27: PV of explicit FCFF FY27E–FY36E | B27: =SUM(B24:K24)
A28: Terminal-year NOPAT (FY37E) | B28: =K17*(1+B4)
A29: Terminal FCFF (after reinvestment at RONIC) | B29: =B28*(1-B4/Inputs!$B$24)
A30: Terminal value at FY36 end | B30: =B29/(WACC!$B$13-B4)
A31: PV of terminal value | B31: =B30/(1+WACC!$B$13)^((DATE(2036,10,31)-Inputs!$B$5)/365.25)
A32: Enterprise value | B32: =B26+B27+B31
A33: Less: gross debt | B33: =-Inputs!$B$8
A34: Plus: cash | B34: =Inputs!$B$9
A35: Less: non-controlling interests | B35: =-Inputs!$B$10
A36: Equity value | B36: =SUM(B32:B35)
A37: Fully diluted shares (m) | B37: =Inputs!$B$7
A38: Value per share ($) | B38: =B36/B37
A39: Terminal value share of EV | B39: =B31/B32
A40: Check: valuation.py value per share | B40: 38.796741

Sheet DCF_Bull
A1: DCF — Bull case (live formulas)
A2: Networking (Oracle, Helios scale-up switches) lifts mix toward 30%+ of revenue at mid/high-20s margins; enterprise AI inference sustains server demand; margins hold near FY27 levels.
A4: Terminal growth | B4: 0.0325
A5: NWC investment (% of Δrevenue) | B5: 0.05
A6: Scenario probability | B6: 0.25
A8: $ millions | B8: FY2027E | C8: FY2028E | D8: FY2029E | E8: FY2030E | F8: FY2031E | G8: FY2032E | H8: FY2033E | I8: FY2034E | J8: FY2035E | K8: FY2036E
A9: Fiscal year end | B9: 2027 | C9: 2028 | D9: 2029 | E9: 2030 | F9: 2031 | G9: 2032 | H9: 2033 | I9: 2034 | J9: 2035 | K9: 2036
A10: Revenue growth | B10: 0.17 | C10: 0.09 | D10: 0.07 | E10: 0.06 | F10: 0.05 | G10: 0.045 | H10: 0.04 | I10: 0.04 | J10: 0.035 | K10: 0.035
A11: Non-GAAP operating margin | B11: 0.15 | C11: 0.15 | D11: 0.148 | E11: 0.145 | F11: 0.145 | G11: 0.145 | H11: 0.145 | I11: 0.145 | J11: 0.145 | K11: 0.145
A12: Revenue | B12: =Inputs!$B$19*(1+B10) | C12: =B12*(1+C10) | D12: =C12*(1+D10) | E12: =D12*(1+E10) | F12: =E12*(1+F10) | G12: =F12*(1+G10) | H12: =G12*(1+H10) | I12: =H12*(1+I10) | J12: =I12*(1+J10) | K12: =J12*(1+K10)
A13: SBC | B13: =B12*Inputs!$B$21 | C13: =C12*Inputs!$B$21 | D13: =D12*Inputs!$B$21 | E13: =E12*Inputs!$B$21 | F13: =F12*Inputs!$B$21 | G13: =G12*Inputs!$B$21 | H13: =H12*Inputs!$B$21 | I13: =I12*Inputs!$B$21 | ... K13: =K12*Inputs!$B$21
A14: Restructuring cash costs | B14: 300 | C14: 150 | D14: 0 | E14: 0 | F14: 0 | G14: 0 | H14: 0 | I14: 0 | J14: 0 | K14: 0
A15: EBIT (after SBC) | B15: =B12*(B11-Inputs!$B$21)-B14 | C15: =C12*(C11-Inputs!$B$21)-C14 | D15: =D12*(D11-Inputs!$B$21)-D14 | E15: =E12*(E11-Inputs!$B$21)-E14 | F15: =F12*(F11-Inputs!$B$21)-F14 | G15: =G12*(G11-Inputs!$B$21)-G14 | H15: =H12*(H11-Inputs!$B$21)-H14 | I15: =I12*(I11-Inputs!$B$21)-I14 | ... K15: =K12*(K11-Inputs!$B$21)-K14
A16: Operating taxes | B16: =B15*Inputs!$B$18 | C16: =C15*Inputs!$B$18 | D16: =D15*Inputs!$B$18 | E16: =E15*Inputs!$B$18 | F16: =F15*Inputs!$B$18 | G16: =G15*Inputs!$B$18 | H16: =H15*Inputs!$B$18 | I16: =I15*Inputs!$B$18 | ... K16: =K15*Inputs!$B$18
A17: NOPAT | B17: =B15-B16 | C17: =C15-C16 | D17: =D15-D16 | E17: =E15-E16 | F17: =F15-F16 | G17: =G15-G16 | H17: =H15-H16 | I17: =I15-I16 | ... K17: =K15-K16
A18: Depreciation | B18: =B12*Inputs!$B$22 | C18: =C12*Inputs!$B$22 | D18: =D12*Inputs!$B$22 | E18: =E12*Inputs!$B$22 | F18: =F12*Inputs!$B$22 | G18: =G12*Inputs!$B$22 | H18: =H12*Inputs!$B$22 | I18: =I12*Inputs!$B$22 | ... K18: =K12*Inputs!$B$22
A19: Net capex | B19: =B12*(Inputs!$B$22+Inputs!$B$23) | C19: =C12*(Inputs!$B$22+Inputs!$B$23) | D19: =D12*(Inputs!$B$22+Inputs!$B$23) | E19: =E12*(Inputs!$B$22+Inputs!$B$23) | F19: =F12*(Inputs!$B$22+Inputs!$B$23) | G19: =G12*(Inputs!$B$22+Inputs!$B$23) | H19: =H12*(Inputs!$B$22+Inputs!$B$23) | I19: =I12*(Inputs!$B$22+Inputs!$B$23) | ... K19: =K12*(Inputs!$B$22+Inputs!$B$23)
A20: Δ Net working capital | B20: =$B$5*(B12-Inputs!$B$19) | C20: =$B$5*(C12-B12) | D20: =$B$5*(D12-C12) | E20: =$B$5*(E12-D12) | F20: =$B$5*(F12-E12) | G20: =$B$5*(G12-F12) | H20: =$B$5*(H12-G12) | I20: =$B$5*(I12-H12) | J20: =$B$5*(J12-I12) | K20: =$B$5*(K12-J12)
A21: FCFF | B21: =B17+B18-B19-B20 | C21: =C17+C18-C19-C20 | D21: =D17+D18-D19-D20 | E21: =E17+E18-E19-E20 | F21: =F17+F18-F19-F20 | G21: =G17+G18-G19-G20 | H21: =H17+H18-H19-H20 | I21: =I17+I18-I19-I20 | ... K21: =K17+K18-K19-K20
A22: Years from valuation date (mid-year) | B22: =(DATE(B9,10,31)-182-Inputs!$B$5)/365.25 | C22: =(DATE(C9,10,31)-182-Inputs!$B$5)/365.25 | D22: =(DATE(D9,10,31)-182-Inputs!$B$5)/365.25 | E22: =(DATE(E9,10,31)-182-Inputs!$B$5)/365.25 | F22: =(DATE(F9,10,31)-182-Inputs!$B$5)/365.25 | G22: =(DATE(G9,10,31)-182-Inputs!$B$5)/365.25 | H22: =(DATE(H9,10,31)-182-Inputs!$B$5)/365.25 | I22: =(DATE(I9,10,31)-182-Inputs!$B$5)/365.25 | ... K22: =(DATE(K9,10,31)-182-Inputs!$B$5)/365.25
A23: Discount factor | B23: =1/(1+WACC!$B$13)^B22 | C23: =1/(1+WACC!$B$13)^C22 | D23: =1/(1+WACC!$B$13)^D22 | E23: =1/(1+WACC!$B$13)^E22 | F23: =1/(1+WACC!$B$13)^F22 | G23: =1/(1+WACC!$B$13)^G22 | H23: =1/(1+WACC!$B$13)^H22 | I23: =1/(1+WACC!$B$13)^I22 | ... K23: =1/(1+WACC!$B$13)^K22
A24: PV of FCFF | B24: =B21*B23 | C24: =C21*C23 | D24: =D21*D23 | E24: =E21*E23 | F24: =F21*F23 | G24: =G21*G23 | H24: =H21*H23 | I24: =I21*I23 | ... K24: =K21*K23
A26: PV of Q4 FY26E stub FCFF | B26: =Inputs!$B$20/(1+WACC!$B$13)^(30/365.25)
A27: PV of explicit FCFF FY27E–FY36E | B27: =SUM(B24:K24)
A28: Terminal-year NOPAT (FY37E) | B28: =K17*(1+B4)
A29: Terminal FCFF (after reinvestment at RONIC) | B29: =B28*(1-B4/Inputs!$B$24)
A30: Terminal value at FY36 end | B30: =B29/(WACC!$B$13-B4)
A31: PV of terminal value | B31: =B30/(1+WACC!$B$13)^((DATE(2036,10,31)-Inputs!$B$5)/365.25)
A32: Enterprise value | B32: =B26+B27+B31
A33: Less: gross debt | B33: =-Inputs!$B$8
A34: Plus: cash | B34: =Inputs!$B$9
A35: Less: non-controlling interests | B35: =-Inputs!$B$10
A36: Equity value | B36: =SUM(B32:B35)
A37: Fully diluted shares (m) | B37: =Inputs!$B$7
A38: Value per share ($) | B38: =B36/B37
A39: Terminal value share of EV | B39: =B31/B32
A40: Check: valuation.py value per share | B40: 53.934936

Sheet Scenarios
A1: Scenario summary
A2: Value per share by scenario and probability-weighted value
A4: Scenario | B4: Probability | C4: Value per share | D4: Weighted
A5: Bear | B5: =DCF_Bear!B6 | C5: =DCF_Bear!B38 | D5: =B5*C5
A6: Base | B6: =DCF_Base!B6 | C6: =DCF_Base!B38 | D6: =B6*C6
A7: Bull | B7: =DCF_Bull!B6 | C7: =DCF_Bull!B38 | D7: =B7*C7
A8: Probability-weighted | D8: =SUM(D5:D7)
A9: vs. price | D9: =D8/Inputs!$B$6-1
A12: Bear | B12: AI-server digestion and memory-cost normalisation reverse FY26 ASP gains; networking share loss to Cisco/Arista; margins revert toward the pre-Juniper mix-adjusted ~10–11%.
A13: Base | B13: FY27 in line with the raised framework (+13–17% revenue, 14–15% non-GAAP margin); growth fades to IDC/Gartner-consistent mid-single digits; margin settles at 12.5% as AI mix offsets networking mix.
A14: Bull | B14: Networking (Oracle, Helios scale-up switches) lifts mix toward 30%+ of revenue at mid/high-20s margins; enterprise AI inference sustains server demand; margins hold near FY27 levels.

Sheet Sens WACC x g
A1: Sens WACC x g
A2: Base-case value per share; computed by code/valuation.py
B4: 2.00% | C4: 2.25% | D4: 2.50% | E4: 2.75% | F4: 3.00% | G4: 3.25%
A5: 8.30% | B5: 45.042152 | C5: 45.540492 | D5: 46.078058 | E5: 46.660149 | F5: 47.293066 | G5: 47.984356
A6: 8.80% | B6: 41.235941 | C6: 41.600159 | D6: 41.990001 | E6: 42.408645 | F6: 42.859814 | G6: 43.347904
A7: 9.30% | B7: 37.948316 | C7: 38.213865 | D7: 38.496039 | E7: 38.796741 | F7: 39.118176 | G7: 39.462914
A8: 9.80% | B8: 35.079597 | C8: 35.271681 | D8: 35.474341 | E8: 35.688703 | F8: 35.916056 | G8: 36.15789
A9: 10.30% | B9: 32.554128 | C9: 32.690984 | D9: 32.834306 | E9: 32.984739 | F9: 33.143011 | G9: 33.309957

Sheet Sens growth x margin
A1: Sens growth x margin
A2: Base-case value per share; computed by code/valuation.py
B4: 10.5% LT margin | C4: 11.5% LT margin | D4: 12.5% LT margin | E4: 13.5% LT margin | F4: 14.5% LT margin
A5: -2% p.a. growth | B5: 25.94969 | C5: 29.332786 | D5: 32.715881 | E5: 36.098976 | F5: 39.482072
A6: -1% p.a. growth | B6: 28.257778 | C6: 31.917868 | D6: 35.577959 | E6: 39.238049 | F6: 42.89814
A7: +0% p.a. growth | B7: 30.74344 | C7: 34.702513 | D7: 38.661587 | E7: 42.62066 | F7: 46.579734
A8: +1% p.a. growth | B8: 33.419752 | C8: 37.701416 | D8: 41.983081 | E8: 46.264746 | F8: 50.546411
A9: +2% p.a. growth | B9: 36.30065 | C9: 40.930241 | D9: 45.559832 | E9: 50.189423 | F9: 54.819015

Sheet Driver sensitivity
A1: Driver sensitivity
A2: One-at-a-time flex of base case
B4: low_case | C4: high_case | D4: range
A5: NWC intensity ±3pp of Δrevenue | B5: 38.361559 | C5: 39.231922 | D5: 0.87036308
A6: Terminal growth ±0.5pp | B6: 38.213865 | C6: 39.462914 | D6: 1.249049
A7: Long-term non-GAAP margin ±1.5pp | B7: 32.722976 | C7: 44.600197 | D7: 11.877221
A8: Revenue growth ±2pp p.a. | B8: 32.843697 | C8: 45.7026 | D8: 12.858903
A9: WACC ±1.0pp | B9: 32.984739 | C9: 46.660149 | D9: 13.67541

Sheet Comps implied
A1: Comps implied
A2: Peer multiples applied to HPE metrics
B4: metric | C4: base_value | D4: multiple_low | E4: multiple_mid | F4: multiple_high | G4: value_low | H4: value_mid | I4: value_high | J4: hpe_current_multiple | K4: note
A5: P/E next FY (core peers) | B5: HPE FY27 consensus non-GAAP EPS | C5: 4.59731 | D5: 7.5292153 | E5: 19.028289 | F5: 23.001055 | G5: 34.614137 | H5: 87.478945 | I5: 105.74298 | J5: 13.505724 | K5: Core peers min–median–max | DELL 23.0x, CSCO 20.0x, NTAP 18.0x, SMCI 7.5x
A6: EV/EBITDA TTM, GAAP basis (core peers) | B6: HPE TTM GAAP EBITDA | C6: 6092 | D6: 6.7489252 | E6: 18.73677 | F6: 22.181646 | G6: 18.699326 | H6: 69.231738 | I6: 83.75294 | J6: 17.042529 | K6: Core peers with data | DELL 22.2x, NTAP 18.7x, SMCI 6.7x
A7: HPE own forward P/E history (FY20–FY24) | B7: HPE FY27 consensus non-GAAP EPS | C7: 4.59731 | D7: 4.4081634 | E7: 7.2524751 | F7: 10.046392 | G7: 20.265694 | H7: 33.341876 | I7: 46.186377 | J7: 13.505724 | K7: Year-end price / next-year actual non-GAAP EPS | FY2020 4.4x, FY2021 7.3x, FY2022 6.6x, FY2023 7.7x, FY2024 10.0x
A8: Sum of the parts (segment EV/EBIT) | B8: TTM segment EBIT after SBC and corporate costs | C8: 4972 | E8: 26.113389 | G8: 66.613437 | H8: 80.08924 | I8: 93.565044 | J8: 20.881555 | K8: Networking EBIT $2,150m × Cisco 29.2x; Cloud & AI EBIT $2,822m × Dell/NetApp median 23.7x; ±15%

Sheet M&A
A1: M&A
A2: Control-premium view
B4: low | C4: high | D4: basis
A5: Control premium 25–35% on 1-month average price | B5: 68.615476 | C5: 74.104714 | D5: 1-month average close $54.89; 25–35% typical US control premium (FactSet/BVR study range); HPE paid 32% for Juniper
A6: Control premium 25–35% on base-case DCF value | B6: 48.495926 | C6: 52.3756 | D6: Strategic value incl. synergies proxied by premium to intrinsic value

Sheet Football field
A1: Football field
A2: Value ranges per share vs $62.09
B4: low | C4: high
A5: 52-week trading range (closes) | B5: 20 | C5: 62.09
A6: Sell-side price targets (low–high) | B6: 52 | C6: 88
A7: DCF: bear to bull scenarios | B7: 22.191359 | C7: 53.934936
A8: DCF base: WACC ±0.5pp, g ±0.25pp | B8: 35.474341 | C8: 42.859814
A9: P/E next FY (core peers) | B9: 34.614137 | C9: 105.74298
A10: EV/EBITDA TTM, GAAP basis (core peers) | B10: 18.699326 | C10: 83.75294
A11: HPE own forward P/E history (FY20–FY24) | B11: 20.265694 | C11: 46.186377
A12: Sum of the parts (segment EV/EBIT) | B12: 66.613437 | C12: 93.565044
A13: Control premium 25–35% on 1-month average price | B13: 68.615476 | C13: 74.104714

Sheet Reverse DCF
A1: Reverse DCF — what $62.09 implies
A2: Solved by bisection in code/valuation.py, holding other base-case drivers
A4: implied long term margin at base growth | B4: 0.18417651
A5: implied growth uplift pp at base margin | B5: 0.058225788
A6: implied wacc at base case | B6: 0.070153287
A7: implied growth uplift if margin holds at fy27 level | B7: 0.035482845
A8: implied fy27 36 revenue cagr at base margin | B8: 0.10846718
A9: base fy27 36 revenue cagr | B9: 0.050214525

Sheet Peer multiples
A1: Peer fundamentals and multiples
A2: TTM from SEC XBRL; prices 11-Sep-2026; forward estimates Yahoo Finance consensus
B4: Company | C4: TTM end | D4: Market cap ($bn) | E4: EV ($bn) | F4: TTM revenue ($bn) | G4: Revenue growth (next FY, cons.) | H4: Gross margin | I4: Operating margin (GAAP) | J4: FCF margin | K4: R&D % revenue | L4: SBC % revenue | M4: Net debt / EBITDA | N4: P/E (TTM GAAP) | O4: P/E (next FY cons.) | P4: P/S (TTM) | Q4: P/B | R4: EV/Revenue (TTM) | S4: EV/EBITDA (TTM GAAP) | T4: EV/EBIT (TTM GAAP) | U4: EV/Revenue (next FY cons.) | V4: FCF yield
A5: HPE | B5: HPE | C5: 2026-07-31 | D5: 82.45552 | E5: 96.48352 | F5: 41.871 | G5: 0.17247731 | H5: 0.36731867 | I5: 0.06214325 | J5: 0.10914475 | K5: 0.088486064 | L5: 0.018986888 | M5: 2.3026921 | N5: 29.543361 | O5: 13.505724 | P5: 1.9692752 | Q5: 3.102631 | R5: 2.3043042 | S5: 15.837741 | T5: 37.080523 | U5: 1.7743925 | V5: 0.055423821
A6: DELL | B6: Dell | C6: 2026-07-31 | D6: 360.6902 | E6: 383.5872 | F6: 151.197 | G6: 0.14769887 | H6: 0.19798673 | I6: 0.09426113 | J6: 0.05661488 | K6: 0.024081166 | L6: 0.0048082965 | M6: 1.3240618 | N6: 31.700668 | O6: 23.001055 | P6: 2.3855645 | Q6: -252.76118 | R6: 2.5370027 | S6: 22.181646 | T6: 26.914623 | U6: 1.7265863 | V6: 0.023732278
A7: SMCI | B7: Supermicro | C7: 2026-06-30 | D7: 26.344311 | E7: 19.055496 | F7: 39.063072 | G7: 0.17328728 | H7: 0.10821604 | I7: 0.070923403 | J7: -0.17847764 | K7: 0.01974325 | L7: 0.01054999 | M7: -2.581495 | N7: 11.811193 | O7: 7.5292153 | P7: 0.67440448 | Q7: 1.8194273 | R7: 0.48781355 | S7: 6.7489252 | T7: 6.8780336 | U7: 0.24193655 | V7: -0.2646448
A8: CSCO | B8: Cisco | C8: 2026-07-25 | D8: 442.08226 | E8: 449.03626 | F8: 63.325 | G8: 0.063343833 | H8: 0.6452428 | I8: 0.24268456 | J8: 0.20161074 | K8: 0.15101461 | L8: 0.060481642 | N8: 33.321946 | O8: 20.015136 | P8: 6.9811647 | Q8: 8.7915334 | R8: 7.0909792 | T8: 29.218913 | U8: 5.7717524 | V8: 0.028879241
A9: ANET | B9: Arista | C9: 2026-06-30 | D9: 251.72782 | E9: 238.38452 | F9: 10.5408 | G9: 0.2755533 | H9: 0.63003757 | I9: 0.43136195 | K9: 0.12962014 | L9: 0.04765293 | M9: -2.8759591 | N9: 62.238002 | O9: 38.678133 | P9: 23.881283 | Q9: 17.01128 | R9: 22.615411 | S9: 51.380404 | T9: 52.427923 | U9: 14.755062
A10: NTAP | B10: NetApp | C10: 2026-07-31 | D10: 39.142379 | E10: 38.054379 | F10: 7.391 | G10: 0.053413634 | H10: 0.70626438 | I10: 0.25016912 | J10: 0.22324449 | K10: 0.13841158 | L10: 0.053713976 | M10: -0.5356967 | N10: 27.603934 | O10: 18.041442 | P10: 5.2959517 | Q10: 26.182193 | R10: 5.1487456 | S10: 18.73677 | T10: 20.58106 | U10: 4.4164281 | V10: 0.0421538
A11: P | B11: Everpure (ex-Pure Storage) | C11: 2026-08-02 | D11: 32.716252 | E11: 31.397182 | F11: 4.26215 | G11: 0.21465001 | H11: 0.69734383 | I11: 0.052604906 | J11: 0.030071443 | K11: 0.24690966 | L11: 0.12901071 | M11: -3.4904342 | N11: 129.16774 | O11: 27.7066 | P11: 7.6759972 | Q11: 21.232765 | R11: 7.3665126 | S11: 83.081108 | T11: 140.03471 | U11: 5.1156747 | V11: 0.0039175943

Sheet Dilution
A1: Dilution — basic to fully diluted shares
A2: capital_structure.py
B4: shares_m | C4: basis | D4: status | E4: pct_of_basic
A5: Common shares outstanding (31-Jul-2026) | B5: 1328 | C5: Q3 FY26 balance sheet | D5: Reported | E5: 1
A6: RSUs / PRSUs (treasury-stock method) | B6: 37 | C6: Q3 FY26 diluted EPS; 75.4m RSUs outstanding at FY25 end | D6: Reported | E6: 0.027861446
A7: 7.625% Series C mandatory convertible preferred (as converted) | B7: 76.056 | C7: 30.0m pref × 2.5352 (min. rate applies above $19.72) | D7: Calculated | E7: 0.057271084
A8: Oracle warrant (max., milestone-vesting) | B8: 4.156466 | C8: Q3 FY26 10-Q; $0.01 exercise price | D8: Reported (upper bound) | E8: 0.003129869
A9: Employee stock options | B9: 0 | C9: Not material in reviewed filings | D9: Data unavailable from the reviewed sources | E9: 0
A10: Convertible notes | B10: 0 | C10: None identified in reviewed filings | D10: Reported | E10: 0
